{
  "info": {
    "author": "ROKO108",
    "author_email": "",
    "bugtrack_url": null,
    "classifiers": [
      "License :: OSI Approved :: MIT License",
      "Operating System :: OS Independent",
      "Programming Language :: Python :: 3"
    ],
    "description": "",
    "description_content_type": "text/markdown",
    "docs_url": null,
    "download_url": "",
    "downloads": {
      "last_day": -1,
      "last_month": -1,
      "last_week": -1
    },
    "home_page": "",
    "keywords": "",
    "license": "",
    "maintainer": "",
    "maintainer_email": "",
    "name": "dbg-print-tool",
    "package_url": "https://pypi.org/project/dbg-print-tool/",
    "platform": null,
    "project_url": "https://pypi.org/project/dbg-print-tool/",
    "project_urls": {
      "Bug Tracker": "https://github.com/ROKO108/dbg/issues",
      "Homepage": "https://github.com/ROKO108/dbg"
    },
    "release_url": "https://pypi.org/project/dbg-print-tool/1.0.22/",
    "requires_dist": null,
    "requires_python": ">=3.8",
    "summary": "Herramienta para debugear codigo",
    "version": "1.0.22",
    "yanked": false,
    "yanked_reason": null
  },
  "last_serial": 16137893,
  "releases": {
    "1.0.0": [
      {
        "comment_text": "",
        "digests": {
          "blake2b_256": "db09200c3f4fa7ec47960a7b6a1d0c803b192ee67c61a05801969cb221331028",
          "md5": "2682f398198611407448d07298f1893b",
          "sha256": "06fc1d4bbbe63d1419a35ec375a416ba23b56ae6c2fd3328a57efa07017d7a5d"
        },
        "downloads": -1,
        "filename": "dbg_print_tool-1.0.0-py3-none-any.whl",
        "has_sig": false,
        "md5_digest": "2682f398198611407448d07298f1893b",
        "packagetype": "bdist_wheel",
        "python_version": "py3",
        "requires_python": ">=3.8",
        "size": 1772,
        "upload_time": "2022-12-15T06:45:22",
        "upload_time_iso_8601": "2022-12-15T06:45:22.452162Z",
        "url": "https://files.pythonhosted.org/packages/db/09/200c3f4fa7ec47960a7b6a1d0c803b192ee67c61a05801969cb221331028/dbg_print_tool-1.0.0-py3-none-any.whl",
        "yanked": false,
        "yanked_reason": null
      },
      {
        "comment_text": "",
        "digests": {
          "blake2b_256": "7559c128fad3721e37bc501854afd657bdc1ae64c659c87fe50f5642eb71e164",
          "md5": "52bf4d3c9e8aa0845950fe50da55c2b5",
          "sha256": "577a72c4ad2aff37541b507ee2ba8e282e021f8300672047d512532bcb1ee3e8"
        },
        "downloads": -1,
        "filename": "dbg-print-tool-1.0.0.tar.gz",
        "has_sig": false,
        "md5_digest": "52bf4d3c9e8aa0845950fe50da55c2b5",
        "packagetype": "sdist",
        "python_version": "source",
        "requires_python": ">=3.8",
        "size": 1573,
        "upload_time": "2022-12-15T06:45:24",
        "upload_time_iso_8601": "2022-12-15T06:45:24.056592Z",
        "url": "https://files.pythonhosted.org/packages/75/59/c128fad3721e37bc501854afd657bdc1ae64c659c87fe50f5642eb71e164/dbg-print-tool-1.0.0.tar.gz",
        "yanked": false,
        "yanked_reason": null
      }
    ],
    "1.0.1": [
      {
        "comment_text": "",
        "digests": {
          "blake2b_256": "39145f186ddcdcca8f99014c637b623385a2c5cfa803b7138e1ce838c7a74be1",
          "md5": "085ef91303cdec1e04f125d5160c4155",
          "sha256": "5bccdf4d5ac320e986386ee55e80ef5c4434538adaf056756903109f553cfe2f"
        },
        "downloads": -1,
        "filename": "dbg_print_tool-1.0.1-py3-none-any.whl",
        "has_sig": false,
        "md5_digest": "085ef91303cdec1e04f125d5160c4155",
        "packagetype": "bdist_wheel",
        "python_version": "py3",
        "requires_python": ">=3.8",
        "size": 1765,
        "upload_time": "2022-12-15T06:54:44",
        "upload_time_iso_8601": "2022-12-15T06:54:44.119253Z",
        "url": "https://files.pythonhosted.org/packages/39/14/5f186ddcdcca8f99014c637b623385a2c5cfa803b7138e1ce838c7a74be1/dbg_print_tool-1.0.1-py3-none-any.whl",
        "yanked": false,
        "yanked_reason": null
      },
      {
        "comment_text": "",
        "digests": {
          "blake2b_256": "a311b9fef3dbc8e9a7104e2e8254dbf1e7d673b5f2760083227b8c192efa0e7a",
          "md5": "ce2ec1f698d2903f969ba63cb5eec330",
          "sha256": "e8abb3762a8cf44a7b515fc551d59f61d29ae6db17b56dc8717a77a6ceebc786"
        },
        "downloads": -1,
        "filename": "dbg-print-tool-1.0.1.tar.gz",
        "has_sig": false,
        "md5_digest": "ce2ec1f698d2903f969ba63cb5eec330",
        "packagetype": "sdist",
        "python_version": "source",
        "requires_python": ">=3.8",
        "size": 1565,
        "upload_time": "2022-12-15T06:54:46",
        "upload_time_iso_8601": "2022-12-15T06:54:46.049973Z",
        "url": "https://files.pythonhosted.org/packages/a3/11/b9fef3dbc8e9a7104e2e8254dbf1e7d673b5f2760083227b8c192efa0e7a/dbg-print-tool-1.0.1.tar.gz",
        "yanked": false,
        "yanked_reason": null
      }
    ],
    "1.0.10": [
      {
        "comment_text": "",
        "digests": {
          "blake2b_256": "2d21500d5aee9b5a0e135101196a73441652f4aa147f3a257b6e5657c23b3e97",
          "md5": "b677a2a2a2956f58672cb3aa54add151",
          "sha256": "575366a3ebb8ec372a1a6d459d394b8835cd6b72ced4e384034e384b006600fb"
        },
        "downloads": -1,
        "filename": "dbg_print_tool-1.0.10-py3-none-any.whl",
        "has_sig": false,
        "md5_digest": "b677a2a2a2956f58672cb3aa54add151",
        "packagetype": "bdist_wheel",
        "python_version": "py3",
        "requires_python": ">=3.8",
        "size": 2407,
        "upload_time": "2022-12-17T21:27:11",
        "upload_time_iso_8601": "2022-12-17T21:27:11.668009Z",
        "url": "https://files.pythonhosted.org/packages/2d/21/500d5aee9b5a0e135101196a73441652f4aa147f3a257b6e5657c23b3e97/dbg_print_tool-1.0.10-py3-none-any.whl",
        "yanked": false,
        "yanked_reason": null
      },
      {
        "comment_text": "",
        "digests": {
          "blake2b_256": "0a05a1962bde37307d12e6f5999072e187ed2b351dfc29d4d330d7e4db34760f",
          "md5": "450879c4ce42db626e5c42657c0b244c",
          "sha256": "aefdeaf96d290ad40387e9408997380df4f20eb10cdc7e8255ab3337bd7e9a1c"
        },
        "downloads": -1,
        "filename": "dbg-print-tool-1.0.10.tar.gz",
        "has_sig": false,
        "md5_digest": "450879c4ce42db626e5c42657c0b244c",
        "packagetype": "sdist",
        "python_version": "source",
        "requires_python": ">=3.8",
        "size": 2040,
        "upload_time": "2022-12-17T21:27:17",
        "upload_time_iso_8601": "2022-12-17T21:27:17.238826Z",
        "url": "https://files.pythonhosted.org/packages/0a/05/a1962bde37307d12e6f5999072e187ed2b351dfc29d4d330d7e4db34760f/dbg-print-tool-1.0.10.tar.gz",
        "yanked": false,
        "yanked_reason": null
      }
    ],
    "1.0.11": [
      {
        "comment_text": "",
        "digests": {
          "blake2b_256": "b5a084f65ab89ba5fcea64fec8e60a02b86fb0eaec9b1a10fcaa32815f3c003c",
          "md5": "6538dae81ac418d3ddc52e13ecb6a868",
          "sha256": "a72c98bfa8f0cfde8ac7429d6bd0b3bb9cd009591afa40e390bf173062316b31"
        },
        "downloads": -1,
        "filename": "dbg_print_tool-1.0.11-py3-none-any.whl",
        "has_sig": false,
        "md5_digest": "6538dae81ac418d3ddc52e13ecb6a868",
        "packagetype": "bdist_wheel",
        "python_version": "py3",
        "requires_python": ">=3.8",
        "size": 1244,
        "upload_time": "2022-12-17T21:39:46",
        "upload_time_iso_8601": "2022-12-17T21:39:46.441557Z",
        "url": "https://files.pythonhosted.org/packages/b5/a0/84f65ab89ba5fcea64fec8e60a02b86fb0eaec9b1a10fcaa32815f3c003c/dbg_print_tool-1.0.11-py3-none-any.whl",
        "yanked": false,
        "yanked_reason": null
      },
      {
        "comment_text": "",
        "digests": {
          "blake2b_256": "741d4d96518d466600868ed27427ae084d8eff09a3f40e7d0c35dced2b48a55a",
          "md5": "25a0f9b9ac0e76270d5821665c2d5466",
          "sha256": "1c1e39d5cad2cfdb407d0bef3f1fe6a49e405c8e014ef2fa06f019932393647c"
        },
        "downloads": -1,
        "filename": "dbg-print-tool-1.0.11.tar.gz",
        "has_sig": false,
        "md5_digest": "25a0f9b9ac0e76270d5821665c2d5466",
        "packagetype": "sdist",
        "python_version": "source",
        "requires_python": ">=3.8",
        "size": 1248,
        "upload_time": "2022-12-17T21:39:52",
        "upload_time_iso_8601": "2022-12-17T21:39:52.638853Z",
        "url": "https://files.pythonhosted.org/packages/74/1d/4d96518d466600868ed27427ae084d8eff09a3f40e7d0c35dced2b48a55a/dbg-print-tool-1.0.11.tar.gz",
        "yanked": false,
        "yanked_reason": null
      }
    ],
    "1.0.12": [
      {
        "comment_text": "",
        "digests": {
          "blake2b_256": "2f7ac3829357b693fbd659fa276275a4da9d20867f909a658598ed60d7d438b7",
          "md5": "2d8216b8b1f678a6612c9a6915ec7741",
          "sha256": "cd45518c746fda7eea2106794b9ff7b7edabacfd605e122105dfd1c08626eef6"
        },
        "downloads": -1,
        "filename": "dbg_print_tool-1.0.12-py3-none-any.whl",
        "has_sig": false,
        "md5_digest": "2d8216b8b1f678a6612c9a6915ec7741",
        "packagetype": "bdist_wheel",
        "python_version": "py3",
        "requires_python": ">=3.8",
        "size": 1245,
        "upload_time": "2022-12-17T21:44:22",
        "upload_time_iso_8601": "2022-12-17T21:44:22.971951Z",
        "url": "https://files.pythonhosted.org/packages/2f/7a/c3829357b693fbd659fa276275a4da9d20867f909a658598ed60d7d438b7/dbg_print_tool-1.0.12-py3-none-any.whl",
        "yanked": false,
        "yanked_reason": null
      },
      {
        "comment_text": "",
        "digests": {
          "blake2b_256": "8dcb5898d4d6cf9683e45563087bb74514fa7aeb3627bff00d24de4564f8ed32",
          "md5": "a0bb8a810e7a92d9804af20139a91434",
          "sha256": "4c02841cb49ccf1a6c0a132542bdbb0b0cedbf720b2a32032f95dcb31020ddc3"
        },
        "downloads": -1,
        "filename": "dbg-print-tool-1.0.12.tar.gz",
        "has_sig": false,
        "md5_digest": "a0bb8a810e7a92d9804af20139a91434",
        "packagetype": "sdist",
        "python_version": "source",
        "requires_python": ">=3.8",
        "size": 1251,
        "upload_time": "2022-12-17T21:44:30",
        "upload_time_iso_8601": "2022-12-17T21:44:30.075109Z",
        "url": "https://files.pythonhosted.org/packages/8d/cb/5898d4d6cf9683e45563087bb74514fa7aeb3627bff00d24de4564f8ed32/dbg-print-tool-1.0.12.tar.gz",
        "yanked": false,
        "yanked_reason": null
      }
    ],
    "1.0.13": [
      {
        "comment_text": "",
        "digests": {
          "blake2b_256": "132727fa2f00cac323a80bc51d614b3b1622f6bbe0411d1d617472330029e5ea",
          "md5": "1d1e28c0262f28e0f5cf30cb2d17b293",
          "sha256": "fa72da4c1650a3321793e5938040b1028954f95fb26367e07f20eb5eadced7d6"
        },
        "downloads": -1,
        "filename": "dbg_print_tool-1.0.13-py3-none-any.whl",
        "has_sig": false,
        "md5_digest": "1d1e28c0262f28e0f5cf30cb2d17b293",
        "packagetype": "bdist_wheel",
        "python_version": "py3",
        "requires_python": ">=3.8",
        "size": 1245,
        "upload_time": "2022-12-17T22:02:41",
        "upload_time_iso_8601": "2022-12-17T22:02:41.633647Z",
        "url": "https://files.pythonhosted.org/packages/13/27/27fa2f00cac323a80bc51d614b3b1622f6bbe0411d1d617472330029e5ea/dbg_print_tool-1.0.13-py3-none-any.whl",
        "yanked": false,
        "yanked_reason": null
      },
      {
        "comment_text": "",
        "digests": {
          "blake2b_256": "9ebd27b68e504d3ed8695629c085d3e8eb345728cf080591a0a09226db5a5a50",
          "md5": "ca866c932ba859a011810608569faff4",
          "sha256": "66121829725dbece60e6e4672fc0ae9f060b7d55f86f6d26d546274215518ffa"
        },
        "downloads": -1,
        "filename": "dbg-print-tool-1.0.13.tar.gz",
        "has_sig": false,
        "md5_digest": "ca866c932ba859a011810608569faff4",
        "packagetype": "sdist",
        "python_version": "source",
        "requires_python": ">=3.8",
        "size": 1223,
        "upload_time": "2022-12-17T22:02:43",
        "upload_time_iso_8601": "2022-12-17T22:02:43.221230Z",
        "url": "https://files.pythonhosted.org/packages/9e/bd/27b68e504d3ed8695629c085d3e8eb345728cf080591a0a09226db5a5a50/dbg-print-tool-1.0.13.tar.gz",
        "yanked": false,
        "yanked_reason": null
      }
    ],
    "1.0.14": [
      {
        "comment_text": "",
        "digests": {
          "blake2b_256": "8d4c2329d67f424cf667024d23ed031223c7a6b6063978a02f8622e1d440f029",
          "md5": "8f61a9b06168d05ea025971f6801ea28",
          "sha256": "96d408553a797d65456238e35e1927a592237f62e18d7aee637926d75f4751d3"
        },
        "downloads": -1,
        "filename": "dbg_print_tool-1.0.14-py3-none-any.whl",
        "has_sig": false,
        "md5_digest": "8f61a9b06168d05ea025971f6801ea28",
        "packagetype": "bdist_wheel",
        "python_version": "py3",
        "requires_python": ">=3.8",
        "size": 2583,
        "upload_time": "2022-12-17T23:48:30",
        "upload_time_iso_8601": "2022-12-17T23:48:30.369394Z",
        "url": "https://files.pythonhosted.org/packages/8d/4c/2329d67f424cf667024d23ed031223c7a6b6063978a02f8622e1d440f029/dbg_print_tool-1.0.14-py3-none-any.whl",
        "yanked": false,
        "yanked_reason": null
      },
      {
        "comment_text": "",
        "digests": {
          "blake2b_256": "cc07d6831ec877f61b78099ff90e0552f12f70a25ed3736bd91d87e0671bf838",
          "md5": "6ed67a01271f9caad940f74484136ade",
          "sha256": "02f543d69fb230c67d1c0fb4b55925a3ee3f874937b6f3ee3757ecccbb3100de"
        },
        "downloads": -1,
        "filename": "dbg-print-tool-1.0.14.tar.gz",
        "has_sig": false,
        "md5_digest": "6ed67a01271f9caad940f74484136ade",
        "packagetype": "sdist",
        "python_version": "source",
        "requires_python": ">=3.8",
        "size": 2200,
        "upload_time": "2022-12-17T23:48:31",
        "upload_time_iso_8601": "2022-12-17T23:48:31.881286Z",
        "url": "https://files.pythonhosted.org/packages/cc/07/d6831ec877f61b78099ff90e0552f12f70a25ed3736bd91d87e0671bf838/dbg-print-tool-1.0.14.tar.gz",
        "yanked": false,
        "yanked_reason": null
      }
    ],
    "1.0.15": [
      {
        "comment_text": "",
        "digests": {
          "blake2b_256": "f5edbd3e10655409d507cdbb6b0468edb85320b6e32eefcd570d7a6c48150ad0",
          "md5": "ed52f7f55620ac02df0eb591e9697fb3",
          "sha256": "3c23824a5ddf24ff1acb718aaf845bb3332be973728ed10a9eb6d302bb374192"
        },
        "downloads": -1,
        "filename": "dbg_print_tool-1.0.15-py3-none-any.whl",
        "has_sig": false,
        "md5_digest": "ed52f7f55620ac02df0eb591e9697fb3",
        "packagetype": "bdist_wheel",
        "python_version": "py3",
        "requires_python": ">=3.8",
        "size": 1245,
        "upload_time": "2022-12-17T23:52:24",
        "upload_time_iso_8601": "2022-12-17T23:52:24.432411Z",
        "url": "https://files.pythonhosted.org/packages/f5/ed/bd3e10655409d507cdbb6b0468edb85320b6e32eefcd570d7a6c48150ad0/dbg_print_tool-1.0.15-py3-none-any.whl",
        "yanked": false,
        "yanked_reason": null
      },
      {
        "comment_text": "",
        "digests": {
          "blake2b_256": "acfae161e502ea8513555be63782c7f63207a19dcd04c0d00e44b74e3b90dccf",
          "md5": "5b1512486a19499d9384c9cfd5c5295f",
          "sha256": "baba71e04c3d0e1a93d87cbd8d9b2c7b12cb2ef8cabb71478e4bf01b5aebfb56"
        },
        "downloads": -1,
        "filename": "dbg-print-tool-1.0.15.tar.gz",
        "has_sig": false,
        "md5_digest": "5b1512486a19499d9384c9cfd5c5295f",
        "packagetype": "sdist",
        "python_version": "source",
        "requires_python": ">=3.8",
        "size": 1227,
        "upload_time": "2022-12-17T23:52:26",
        "upload_time_iso_8601": "2022-12-17T23:52:26.201637Z",
        "url": "https://files.pythonhosted.org/packages/ac/fa/e161e502ea8513555be63782c7f63207a19dcd04c0d00e44b74e3b90dccf/dbg-print-tool-1.0.15.tar.gz",
        "yanked": false,
        "yanked_reason": null
      }
    ],
    "1.0.16": [
      {
        "comment_text": "",
        "digests": {
          "blake2b_256": "0a6d29177c69efe95642f5eecea53448c0e285808c1b9f13172c0dfa2a4e2cf1",
          "md5": "4f839c908a198b3cb9ff94d7a8cfe1c4",
          "sha256": "38f2d66136d58ff88ab6c23139c22fe8cc2e2ab01419544d3ed7d71dcbb7c4ed"
        },
        "downloads": -1,
        "filename": "dbg_print_tool-1.0.16-py3-none-any.whl",
        "has_sig": false,
        "md5_digest": "4f839c908a198b3cb9ff94d7a8cfe1c4",
        "packagetype": "bdist_wheel",
        "python_version": "py3",
        "requires_python": ">=3.8",
        "size": 2559,
        "upload_time": "2022-12-17T23:57:01",
        "upload_time_iso_8601": "2022-12-17T23:57:01.848141Z",
        "url": "https://files.pythonhosted.org/packages/0a/6d/29177c69efe95642f5eecea53448c0e285808c1b9f13172c0dfa2a4e2cf1/dbg_print_tool-1.0.16-py3-none-any.whl",
        "yanked": false,
        "yanked_reason": null
      },
      {
        "comment_text": "",
        "digests": {
          "blake2b_256": "27800bcf8a14992519af803dba2559c76849bf290b491e697c69eb5d55cc81a1",
          "md5": "d71b51e104ab1499257b02fb3f4118ec",
          "sha256": "e081c9ca2b70c3f8fe3f0282640a961ded524451b88e5de33040c285df03fe49"
        },
        "downloads": -1,
        "filename": "dbg-print-tool-1.0.16.tar.gz",
        "has_sig": false,
        "md5_digest": "d71b51e104ab1499257b02fb3f4118ec",
        "packagetype": "sdist",
        "python_version": "source",
        "requires_python": ">=3.8",
        "size": 2111,
        "upload_time": "2022-12-17T23:57:03",
        "upload_time_iso_8601": "2022-12-17T23:57:03.725636Z",
        "url": "https://files.pythonhosted.org/packages/27/80/0bcf8a14992519af803dba2559c76849bf290b491e697c69eb5d55cc81a1/dbg-print-tool-1.0.16.tar.gz",
        "yanked": false,
        "yanked_reason": null
      }
    ],
    "1.0.17": [
      {
        "comment_text": "",
        "digests": {
          "blake2b_256": "a454ad7f2c202cc0d825f5ad0077a20029279fbd3c64c46312015edb4ae6c08b",
          "md5": "0e96f9f163bec82a839306a527b8a0e2",
          "sha256": "3b90416e1697a8c391c2cbae8ed33b2aacc68f5024059ec37fdaad0d3a18ce1a"
        },
        "downloads": -1,
        "filename": "dbg_print_tool-1.0.17-py3-none-any.whl",
        "has_sig": false,
        "md5_digest": "0e96f9f163bec82a839306a527b8a0e2",
        "packagetype": "bdist_wheel",
        "python_version": "py3",
        "requires_python": ">=3.8",
        "size": 2581,
        "upload_time": "2022-12-18T00:02:42",
        "upload_time_iso_8601": "2022-12-18T00:02:42.623708Z",
        "url": "https://files.pythonhosted.org/packages/a4/54/ad7f2c202cc0d825f5ad0077a20029279fbd3c64c46312015edb4ae6c08b/dbg_print_tool-1.0.17-py3-none-any.whl",
        "yanked": false,
        "yanked_reason": null
      },
      {
        "comment_text": "",
        "digests": {
          "blake2b_256": "a258ed5b55ce1b5115746450c428a41ace34e2f92840d89a8c7baabb9484920b",
          "md5": "7e0b5a5c71776b003e0701cc9e5bba06",
          "sha256": "9a95a1f3b19b38460a7a7973f5dae45f14b785cd70e34d047949e72fa18684c6"
        },
        "downloads": -1,
        "filename": "dbg-print-tool-1.0.17.tar.gz",
        "has_sig": false,
        "md5_digest": "7e0b5a5c71776b003e0701cc9e5bba06",
        "packagetype": "sdist",
        "python_version": "source",
        "requires_python": ">=3.8",
        "size": 2102,
        "upload_time": "2022-12-18T00:02:43",
        "upload_time_iso_8601": "2022-12-18T00:02:43.836650Z",
        "url": "https://files.pythonhosted.org/packages/a2/58/ed5b55ce1b5115746450c428a41ace34e2f92840d89a8c7baabb9484920b/dbg-print-tool-1.0.17.tar.gz",
        "yanked": false,
        "yanked_reason": null
      }
    ],
    "1.0.18": [
      {
        "comment_text": "",
        "digests": {
          "blake2b_256": "822739208eb2ed36c93e07861d84fdfa8a2b2e05152a9d62d6c90ba78f01d64e",
          "md5": "ee635d21b9f797fc54ccdb0ed8da9131",
          "sha256": "e5340289d7cd520824a7eedda21a149b4f0e828ea083ee5e7e5c05296ff9d817"
        },
        "downloads": -1,
        "filename": "dbg_print_tool-1.0.18-py3-none-any.whl",
        "has_sig": false,
        "md5_digest": "ee635d21b9f797fc54ccdb0ed8da9131",
        "packagetype": "bdist_wheel",
        "python_version": "py3",
        "requires_python": ">=3.8",
        "size": 2605,
        "upload_time": "2022-12-18T00:10:17",
        "upload_time_iso_8601": "2022-12-18T00:10:17.168726Z",
        "url": "https://files.pythonhosted.org/packages/82/27/39208eb2ed36c93e07861d84fdfa8a2b2e05152a9d62d6c90ba78f01d64e/dbg_print_tool-1.0.18-py3-none-any.whl",
        "yanked": false,
        "yanked_reason": null
      },
      {
        "comment_text": "",
        "digests": {
          "blake2b_256": "21472316d4caff13ff55187427a9734c5e76957b954300997fb6c504cbd42f01",
          "md5": "4c2b4df8abd3d63452de4e1c0af1d177",
          "sha256": "7b0e11e8acb449b532c4c942fdf085f8b6b69bfd439015c82c79548ac79ff0a3"
        },
        "downloads": -1,
        "filename": "dbg-print-tool-1.0.18.tar.gz",
        "has_sig": false,
        "md5_digest": "4c2b4df8abd3d63452de4e1c0af1d177",
        "packagetype": "sdist",
        "python_version": "source",
        "requires_python": ">=3.8",
        "size": 2122,
        "upload_time": "2022-12-18T00:10:18",
        "upload_time_iso_8601": "2022-12-18T00:10:18.471349Z",
        "url": "https://files.pythonhosted.org/packages/21/47/2316d4caff13ff55187427a9734c5e76957b954300997fb6c504cbd42f01/dbg-print-tool-1.0.18.tar.gz",
        "yanked": false,
        "yanked_reason": null
      }
    ],
    "1.0.19": [
      {
        "comment_text": "",
        "digests": {
          "blake2b_256": "7064d8c83399c18e4c979d9a4164c934492e40e95f167daf5bb7096635953595",
          "md5": "277de0bbaf90762c130b139442ef37ff",
          "sha256": "d4e5732f8dbd3880644fff70544e9206866ff423b4fc8d9090b253c174869cd0"
        },
        "downloads": -1,
        "filename": "dbg_print_tool-1.0.19-py3-none-any.whl",
        "has_sig": false,
        "md5_digest": "277de0bbaf90762c130b139442ef37ff",
        "packagetype": "bdist_wheel",
        "python_version": "py3",
        "requires_python": ">=3.8",
        "size": 2578,
        "upload_time": "2022-12-18T00:14:06",
        "upload_time_iso_8601": "2022-12-18T00:14:06.726883Z",
        "url": "https://files.pythonhosted.org/packages/70/64/d8c83399c18e4c979d9a4164c934492e40e95f167daf5bb7096635953595/dbg_print_tool-1.0.19-py3-none-any.whl",
        "yanked": false,
        "yanked_reason": null
      },
      {
        "comment_text": "",
        "digests": {
          "blake2b_256": "22aa04e01df6a9f5e5777f04ffef01ccf61cfab30b9b36ddb8f2e97e66c6a54d",
          "md5": "341884c40700304f8647502257cae44f",
          "sha256": "094d0dbec6a3d597c229426f580325d3f758be3ad37465497027905c24482281"
        },
        "downloads": -1,
        "filename": "dbg-print-tool-1.0.19.tar.gz",
        "has_sig": false,
        "md5_digest": "341884c40700304f8647502257cae44f",
        "packagetype": "sdist",
        "python_version": "source",
        "requires_python": ">=3.8",
        "size": 2098,
        "upload_time": "2022-12-18T00:14:08",
        "upload_time_iso_8601": "2022-12-18T00:14:08.426590Z",
        "url": "https://files.pythonhosted.org/packages/22/aa/04e01df6a9f5e5777f04ffef01ccf61cfab30b9b36ddb8f2e97e66c6a54d/dbg-print-tool-1.0.19.tar.gz",
        "yanked": false,
        "yanked_reason": null
      }
    ],
    "1.0.2": [
      {
        "comment_text": "",
        "digests": {
          "blake2b_256": "2d27d56d2362a24679b010b65e3fe9aaad3162b2b02bcf2e3fb388182c00086e",
          "md5": "9df19614b6ee2ab9af0030675db1bea7",
          "sha256": "9b084ecbbc7bc331721863a53e254edd5ca831c2ad05d942330102db942358d6"
        },
        "downloads": -1,
        "filename": "dbg_print_tool-1.0.2-py3-none-any.whl",
        "has_sig": false,
        "md5_digest": "9df19614b6ee2ab9af0030675db1bea7",
        "packagetype": "bdist_wheel",
        "python_version": "py3",
        "requires_python": ">=3.8",
        "size": 1911,
        "upload_time": "2022-12-15T20:11:44",
        "upload_time_iso_8601": "2022-12-15T20:11:44.980390Z",
        "url": "https://files.pythonhosted.org/packages/2d/27/d56d2362a24679b010b65e3fe9aaad3162b2b02bcf2e3fb388182c00086e/dbg_print_tool-1.0.2-py3-none-any.whl",
        "yanked": false,
        "yanked_reason": null
      },
      {
        "comment_text": "",
        "digests": {
          "blake2b_256": "18c3d91aa954291e8f1b36c177dcd42e38984d5493d1bf610725ad9e3f705e5d",
          "md5": "1aeedda561228f815c75435ae3c13ab8",
          "sha256": "c621d9ef500cc032ca6bc552e1d2b46d0f4168bacf1fad9743deb1f867ae074c"
        },
        "downloads": -1,
        "filename": "dbg-print-tool-1.0.2.tar.gz",
        "has_sig": false,
        "md5_digest": "1aeedda561228f815c75435ae3c13ab8",
        "packagetype": "sdist",
        "python_version": "source",
        "requires_python": ">=3.8",
        "size": 1710,
        "upload_time": "2022-12-15T20:11:47",
        "upload_time_iso_8601": "2022-12-15T20:11:47.687956Z",
        "url": "https://files.pythonhosted.org/packages/18/c3/d91aa954291e8f1b36c177dcd42e38984d5493d1bf610725ad9e3f705e5d/dbg-print-tool-1.0.2.tar.gz",
        "yanked": false,
        "yanked_reason": null
      }
    ],
    "1.0.20": [
      {
        "comment_text": "",
        "digests": {
          "blake2b_256": "cebe9b2fee047bc65e3d4701df33922899bb8b5c636290fed2a0f908f7c52ae7",
          "md5": "c0b4537fde24402496d6b8e2f380f8e3",
          "sha256": "12f144e0c76fb3206735cf51bb06a4908d1f4b5cbca99db658cac316ab434f7e"
        },
        "downloads": -1,
        "filename": "dbg_print_tool-1.0.20-py3-none-any.whl",
        "has_sig": false,
        "md5_digest": "c0b4537fde24402496d6b8e2f380f8e3",
        "packagetype": "bdist_wheel",
        "python_version": "py3",
        "requires_python": ">=3.8",
        "size": 2590,
        "upload_time": "2022-12-18T00:27:30",
        "upload_time_iso_8601": "2022-12-18T00:27:30.189446Z",
        "url": "https://files.pythonhosted.org/packages/ce/be/9b2fee047bc65e3d4701df33922899bb8b5c636290fed2a0f908f7c52ae7/dbg_print_tool-1.0.20-py3-none-any.whl",
        "yanked": false,
        "yanked_reason": null
      },
      {
        "comment_text": "",
        "digests": {
          "blake2b_256": "01b82c79645d12dd6078231eadac85c6b67f3840b78380f09f2ad815d7242e4a",
          "md5": "e6a43562822171e83b5d64fff4f45bc6",
          "sha256": "c25bb779d8dc71f3dd858de32e6553fa7cf9477bc3561ccbcb7159314ef08453"
        },
        "downloads": -1,
        "filename": "dbg-print-tool-1.0.20.tar.gz",
        "has_sig": false,
        "md5_digest": "e6a43562822171e83b5d64fff4f45bc6",
        "packagetype": "sdist",
        "python_version": "source",
        "requires_python": ">=3.8",
        "size": 2145,
        "upload_time": "2022-12-18T00:27:31",
        "upload_time_iso_8601": "2022-12-18T00:27:31.514809Z",
        "url": "https://files.pythonhosted.org/packages/01/b8/2c79645d12dd6078231eadac85c6b67f3840b78380f09f2ad815d7242e4a/dbg-print-tool-1.0.20.tar.gz",
        "yanked": false,
        "yanked_reason": null
      }
    ],
    "1.0.21": [
      {
        "comment_text": "",
        "digests": {
          "blake2b_256": "f3b1b3a83341c074f3c7441fb30d45e254b7120cc9dfb49cf84ad1998f23031d",
          "md5": "7aabd90c34b46ca3aeaa99f95b90f300",
          "sha256": "f7e89c4ecdf10d0530896faf34aa26899d1f0fd32f56cb7afbe7d04690e37e34"
        },
        "downloads": -1,
        "filename": "dbg_print_tool-1.0.21-py3-none-any.whl",
        "has_sig": false,
        "md5_digest": "7aabd90c34b46ca3aeaa99f95b90f300",
        "packagetype": "bdist_wheel",
        "python_version": "py3",
        "requires_python": ">=3.8",
        "size": 2714,
        "upload_time": "2022-12-18T01:00:38",
        "upload_time_iso_8601": "2022-12-18T01:00:38.675486Z",
        "url": "https://files.pythonhosted.org/packages/f3/b1/b3a83341c074f3c7441fb30d45e254b7120cc9dfb49cf84ad1998f23031d/dbg_print_tool-1.0.21-py3-none-any.whl",
        "yanked": false,
        "yanked_reason": null
      },
      {
        "comment_text": "",
        "digests": {
          "blake2b_256": "86f8272c62bd1c80d4c5f2b496244903f0672a2233973fc0f76bad760af46f5a",
          "md5": "037d63ef92cef6c92b0cb2212a6f5554",
          "sha256": "4e1a0a2714d8074fd835ab29ce990f966fca74630582e0a2f5f2962bcc79c292"
        },
        "downloads": -1,
        "filename": "dbg-print-tool-1.0.21.tar.gz",
        "has_sig": false,
        "md5_digest": "037d63ef92cef6c92b0cb2212a6f5554",
        "packagetype": "sdist",
        "python_version": "source",
        "requires_python": ">=3.8",
        "size": 2219,
        "upload_time": "2022-12-18T01:00:40",
        "upload_time_iso_8601": "2022-12-18T01:00:40.183428Z",
        "url": "https://files.pythonhosted.org/packages/86/f8/272c62bd1c80d4c5f2b496244903f0672a2233973fc0f76bad760af46f5a/dbg-print-tool-1.0.21.tar.gz",
        "yanked": false,
        "yanked_reason": null
      }
    ],
    "1.0.22": [
      {
        "comment_text": "",
        "digests": {
          "blake2b_256": "847497fe04d869e399fea2cd2cd63faa07a3a8e7a69773951f9c48118e565c25",
          "md5": "f0816934c34da960a220ca9052c8f94d",
          "sha256": "c7292d4fc6e7188dd03cd29b762afc5af6de1e48203b859d2a2b66551fed41fc"
        },
        "downloads": -1,
        "filename": "dbg_print_tool-1.0.22-py3-none-any.whl",
        "has_sig": false,
        "md5_digest": "f0816934c34da960a220ca9052c8f94d",
        "packagetype": "bdist_wheel",
        "python_version": "py3",
        "requires_python": ">=3.8",
        "size": 2714,
        "upload_time": "2022-12-18T01:09:16",
        "upload_time_iso_8601": "2022-12-18T01:09:16.448280Z",
        "url": "https://files.pythonhosted.org/packages/84/74/97fe04d869e399fea2cd2cd63faa07a3a8e7a69773951f9c48118e565c25/dbg_print_tool-1.0.22-py3-none-any.whl",
        "yanked": false,
        "yanked_reason": null
      },
      {
        "comment_text": "",
        "digests": {
          "blake2b_256": "5cff8045e3b23224a7a5a35fcd9db1cf19c587166103dc366637f972ee551587",
          "md5": "0a746911390ea473c1d410aab6b28079",
          "sha256": "a6027ca665a6b39e717c1d42954a3515d3fd895aab66680391a02c3335ca395f"
        },
        "downloads": -1,
        "filename": "dbg-print-tool-1.0.22.tar.gz",
        "has_sig": false,
        "md5_digest": "0a746911390ea473c1d410aab6b28079",
        "packagetype": "sdist",
        "python_version": "source",
        "requires_python": ">=3.8",
        "size": 2234,
        "upload_time": "2022-12-18T01:09:17",
        "upload_time_iso_8601": "2022-12-18T01:09:17.606270Z",
        "url": "https://files.pythonhosted.org/packages/5c/ff/8045e3b23224a7a5a35fcd9db1cf19c587166103dc366637f972ee551587/dbg-print-tool-1.0.22.tar.gz",
        "yanked": false,
        "yanked_reason": null
      }
    ],
    "1.0.3": [
      {
        "comment_text": "",
        "digests": {
          "blake2b_256": "b0fb54565189b1866b6aaf549ba3065b6be25f22990d4d7a63c0de50aa69e79c",
          "md5": "f96759effb1559a637f3a4f4a35364a0",
          "sha256": "032573edf9d61a57cd50ff7c570ba78d45a85317155b9fb191e33ecaa46d0e2b"
        },
        "downloads": -1,
        "filename": "dbg_print_tool-1.0.3-py3-none-any.whl",
        "has_sig": false,
        "md5_digest": "f96759effb1559a637f3a4f4a35364a0",
        "packagetype": "bdist_wheel",
        "python_version": "py3",
        "requires_python": ">=3.8",
        "size": 1942,
        "upload_time": "2022-12-15T23:14:29",
        "upload_time_iso_8601": "2022-12-15T23:14:29.402507Z",
        "url": "https://files.pythonhosted.org/packages/b0/fb/54565189b1866b6aaf549ba3065b6be25f22990d4d7a63c0de50aa69e79c/dbg_print_tool-1.0.3-py3-none-any.whl",
        "yanked": false,
        "yanked_reason": null
      },
      {
        "comment_text": "",
        "digests": {
          "blake2b_256": "fc38fb920e486fb07a31efebb68c867111d9e33c54a99105694102107b1aa43c",
          "md5": "6629cd75dd110abd064cc634434d4dac",
          "sha256": "6be3fe0e5d78dd75adcb13fdbb2ee26faf8b28199d1f2da5863f4b1a029bd13a"
        },
        "downloads": -1,
        "filename": "dbg-print-tool-1.0.3.tar.gz",
        "has_sig": false,
        "md5_digest": "6629cd75dd110abd064cc634434d4dac",
        "packagetype": "sdist",
        "python_version": "source",
        "requires_python": ">=3.8",
        "size": 1738,
        "upload_time": "2022-12-15T23:14:32",
        "upload_time_iso_8601": "2022-12-15T23:14:32.159581Z",
        "url": "https://files.pythonhosted.org/packages/fc/38/fb920e486fb07a31efebb68c867111d9e33c54a99105694102107b1aa43c/dbg-print-tool-1.0.3.tar.gz",
        "yanked": false,
        "yanked_reason": null
      }
    ],
    "1.0.4": [
      {
        "comment_text": "",
        "digests": {
          "blake2b_256": "0b14a0aa27b23d0b34070b380dc12fe4c5ca97d946dcf4cb4a39369f14a71153",
          "md5": "c9a2fa5d8f76ad9a6e821efa1dfc4579",
          "sha256": "42597a76c1a0d446381f8c17039fa6d79ab8d4403910d2d64adbf9fe8cf85bb5"
        },
        "downloads": -1,
        "filename": "dbg_print_tool-1.0.4-py3-none-any.whl",
        "has_sig": false,
        "md5_digest": "c9a2fa5d8f76ad9a6e821efa1dfc4579",
        "packagetype": "bdist_wheel",
        "python_version": "py3",
        "requires_python": ">=3.8",
        "size": 1962,
        "upload_time": "2022-12-15T23:39:13",
        "upload_time_iso_8601": "2022-12-15T23:39:13.933374Z",
        "url": "https://files.pythonhosted.org/packages/0b/14/a0aa27b23d0b34070b380dc12fe4c5ca97d946dcf4cb4a39369f14a71153/dbg_print_tool-1.0.4-py3-none-any.whl",
        "yanked": false,
        "yanked_reason": null
      },
      {
        "comment_text": "",
        "digests": {
          "blake2b_256": "2019a5e225ddbe832dc8817b95bb065c45f3471c213a4090a640f37eda8ef23e",
          "md5": "00ea613b172bf9d4f11b59beb2a29fb2",
          "sha256": "00a29a6b67505d3733fad4ca9b98cfa88fbcdc6053284bdcdc4b9b4aa09893f8"
        },
        "downloads": -1,
        "filename": "dbg-print-tool-1.0.4.tar.gz",
        "has_sig": false,
        "md5_digest": "00ea613b172bf9d4f11b59beb2a29fb2",
        "packagetype": "sdist",
        "python_version": "source",
        "requires_python": ">=3.8",
        "size": 1772,
        "upload_time": "2022-12-15T23:39:16",
        "upload_time_iso_8601": "2022-12-15T23:39:16.970037Z",
        "url": "https://files.pythonhosted.org/packages/20/19/a5e225ddbe832dc8817b95bb065c45f3471c213a4090a640f37eda8ef23e/dbg-print-tool-1.0.4.tar.gz",
        "yanked": false,
        "yanked_reason": null
      }
    ],
    "1.0.5": [
      {
        "comment_text": "",
        "digests": {
          "blake2b_256": "d961a3d3edea06facb261db9caf655f445ccce0a633d11e23cb8ea30cbe25598",
          "md5": "877a24e5bb220a2fa446b0bf23df73ad",
          "sha256": "74bbcc97fd49356ff4e478618c306c10d97646f98575764824665f30b2ec6ec6"
        },
        "downloads": -1,
        "filename": "dbg_print_tool-1.0.5-py3-none-any.whl",
        "has_sig": false,
        "md5_digest": "877a24e5bb220a2fa446b0bf23df73ad",
        "packagetype": "bdist_wheel",
        "python_version": "py3",
        "requires_python": ">=3.8",
        "size": 1970,
        "upload_time": "2022-12-16T01:18:09",
        "upload_time_iso_8601": "2022-12-16T01:18:09.106049Z",
        "url": "https://files.pythonhosted.org/packages/d9/61/a3d3edea06facb261db9caf655f445ccce0a633d11e23cb8ea30cbe25598/dbg_print_tool-1.0.5-py3-none-any.whl",
        "yanked": false,
        "yanked_reason": null
      },
      {
        "comment_text": "",
        "digests": {
          "blake2b_256": "76f45682b6ec9ad13652e990e18f07baad680a1454c3c71d3d9866918eb0283b",
          "md5": "69cd878444127c6eb3bb09a6221a4019",
          "sha256": "5c122fad14fd5df7e69219979e2a0a3d5d276dae5c0e7ed15250d19b78cf5d86"
        },
        "downloads": -1,
        "filename": "dbg-print-tool-1.0.5.tar.gz",
        "has_sig": false,
        "md5_digest": "69cd878444127c6eb3bb09a6221a4019",
        "packagetype": "sdist",
        "python_version": "source",
        "requires_python": ">=3.8",
        "size": 1782,
        "upload_time": "2022-12-16T01:18:13",
        "upload_time_iso_8601": "2022-12-16T01:18:13.604703Z",
        "url": "https://files.pythonhosted.org/packages/76/f4/5682b6ec9ad13652e990e18f07baad680a1454c3c71d3d9866918eb0283b/dbg-print-tool-1.0.5.tar.gz",
        "yanked": false,
        "yanked_reason": null
      }
    ],
    "1.0.6": [
      {
        "comment_text": "",
        "digests": {
          "blake2b_256": "e4d6cba10086868a9943b168079cea6edeaf3b116c5596e7a21e87cf85651cd5",
          "md5": "71314413ada7874cd4cdbf49e8fa5663",
          "sha256": "55b71b67df0eaeea4793c9eb96adce1e1393b6cff65c9f3c0075620aae19d846"
        },
        "downloads": -1,
        "filename": "dbg_print_tool-1.0.6-py3-none-any.whl",
        "has_sig": false,
        "md5_digest": "71314413ada7874cd4cdbf49e8fa5663",
        "packagetype": "bdist_wheel",
        "python_version": "py3",
        "requires_python": ">=3.8",
        "size": 2005,
        "upload_time": "2022-12-16T01:26:51",
        "upload_time_iso_8601": "2022-12-16T01:26:51.504741Z",
        "url": "https://files.pythonhosted.org/packages/e4/d6/cba10086868a9943b168079cea6edeaf3b116c5596e7a21e87cf85651cd5/dbg_print_tool-1.0.6-py3-none-any.whl",
        "yanked": false,
        "yanked_reason": null
      },
      {
        "comment_text": "",
        "digests": {
          "blake2b_256": "4905a320838242b5a06496d93db58e89ea89f6af4e0554640407c35bb491d932",
          "md5": "6a0d132887b5ecea251078a166a3ef7e",
          "sha256": "e9f0848fb16b21248dc3a00f6ec239aef2e2c0e307cccf5807c7bb194ee0f867"
        },
        "downloads": -1,
        "filename": "dbg-print-tool-1.0.6.tar.gz",
        "has_sig": false,
        "md5_digest": "6a0d132887b5ecea251078a166a3ef7e",
        "packagetype": "sdist",
        "python_version": "source",
        "requires_python": ">=3.8",
        "size": 1802,
        "upload_time": "2022-12-16T01:26:55",
        "upload_time_iso_8601": "2022-12-16T01:26:55.465448Z",
        "url": "https://files.pythonhosted.org/packages/49/05/a320838242b5a06496d93db58e89ea89f6af4e0554640407c35bb491d932/dbg-print-tool-1.0.6.tar.gz",
        "yanked": false,
        "yanked_reason": null
      }
    ],
    "1.0.7": [
      {
        "comment_text": "",
        "digests": {
          "blake2b_256": "b366bdb1f5bf8e4307b0bf6f632840965094729f74042a5d57b1f77102c72134",
          "md5": "3dc49948bf9e2e7d8b1ca7d0b1acc82a",
          "sha256": "6cea518892514ceeee6bcccbe8a927a67366d108158b9a351798d0262604c6b7"
        },
        "downloads": -1,
        "filename": "dbg_print_tool-1.0.7-py3-none-any.whl",
        "has_sig": false,
        "md5_digest": "3dc49948bf9e2e7d8b1ca7d0b1acc82a",
        "packagetype": "bdist_wheel",
        "python_version": "py3",
        "requires_python": ">=3.8",
        "size": 2000,
        "upload_time": "2022-12-16T01:36:01",
        "upload_time_iso_8601": "2022-12-16T01:36:01.772105Z",
        "url": "https://files.pythonhosted.org/packages/b3/66/bdb1f5bf8e4307b0bf6f632840965094729f74042a5d57b1f77102c72134/dbg_print_tool-1.0.7-py3-none-any.whl",
        "yanked": false,
        "yanked_reason": null
      },
      {
        "comment_text": "",
        "digests": {
          "blake2b_256": "667861498462578c3b3fc78a342dc5c9adf4237fa1284a1df185fdd124337d28",
          "md5": "f8e02b3dd77293c5972d6590febac3e3",
          "sha256": "4ceffd6b6a4e4c014c95d761c08ee132d185767804c8910bbb239e2f34b079f9"
        },
        "downloads": -1,
        "filename": "dbg-print-tool-1.0.7.tar.gz",
        "has_sig": false,
        "md5_digest": "f8e02b3dd77293c5972d6590febac3e3",
        "packagetype": "sdist",
        "python_version": "source",
        "requires_python": ">=3.8",
        "size": 1810,
        "upload_time": "2022-12-16T01:36:06",
        "upload_time_iso_8601": "2022-12-16T01:36:06.822019Z",
        "url": "https://files.pythonhosted.org/packages/66/78/61498462578c3b3fc78a342dc5c9adf4237fa1284a1df185fdd124337d28/dbg-print-tool-1.0.7.tar.gz",
        "yanked": false,
        "yanked_reason": null
      }
    ],
    "1.0.8": [
      {
        "comment_text": "",
        "digests": {
          "blake2b_256": "925eb89e8d480a99d44a7a39fae1ddd2402bf2b42a1448fc7834dd3075011d86",
          "md5": "c09e205d774fe23cf0cf174e93634efb",
          "sha256": "f94b618343afc1d1d6d5f0b0d0ff378e4e9bd042a7fc51d5b9403215416dcef8"
        },
        "downloads": -1,
        "filename": "dbg_print_tool-1.0.8-py3-none-any.whl",
        "has_sig": false,
        "md5_digest": "c09e205d774fe23cf0cf174e93634efb",
        "packagetype": "bdist_wheel",
        "python_version": "py3",
        "requires_python": ">=3.8",
        "size": 2021,
        "upload_time": "2022-12-16T01:50:48",
        "upload_time_iso_8601": "2022-12-16T01:50:48.881580Z",
        "url": "https://files.pythonhosted.org/packages/92/5e/b89e8d480a99d44a7a39fae1ddd2402bf2b42a1448fc7834dd3075011d86/dbg_print_tool-1.0.8-py3-none-any.whl",
        "yanked": false,
        "yanked_reason": null
      },
      {
        "comment_text": "",
        "digests": {
          "blake2b_256": "edb985f67f873412bf4c154d0968ad0f8ff1113c010190c60af11d4bb9b42ba4",
          "md5": "9a181aed531704559052e5148bedd90c",
          "sha256": "625f42a75d6f8f3b704def0c5caf93625ad191100a72658ddaeb19258fd22876"
        },
        "downloads": -1,
        "filename": "dbg-print-tool-1.0.8.tar.gz",
        "has_sig": false,
        "md5_digest": "9a181aed531704559052e5148bedd90c",
        "packagetype": "sdist",
        "python_version": "source",
        "requires_python": ">=3.8",
        "size": 1841,
        "upload_time": "2022-12-16T01:50:53",
        "upload_time_iso_8601": "2022-12-16T01:50:53.439546Z",
        "url": "https://files.pythonhosted.org/packages/ed/b9/85f67f873412bf4c154d0968ad0f8ff1113c010190c60af11d4bb9b42ba4/dbg-print-tool-1.0.8.tar.gz",
        "yanked": false,
        "yanked_reason": null
      }
    ],
    "1.0.9": [
      {
        "comment_text": "",
        "digests": {
          "blake2b_256": "c7b119008d060d4a8216b7cbf279b200cf97f41bd3b209f4eb63656ababbe2e2",
          "md5": "1338f0659bd1738ed93bb83fa66d6e7e",
          "sha256": "5126cf5d2dde006deea2f2ed4acc81f419d7d0d7e82c5e52357b2f13fcc0b714"
        },
        "downloads": -1,
        "filename": "dbg_print_tool-1.0.9-py3-none-any.whl",
        "has_sig": false,
        "md5_digest": "1338f0659bd1738ed93bb83fa66d6e7e",
        "packagetype": "bdist_wheel",
        "python_version": "py3",
        "requires_python": ">=3.8",
        "size": 2431,
        "upload_time": "2022-12-17T21:24:16",
        "upload_time_iso_8601": "2022-12-17T21:24:16.120388Z",
        "url": "https://files.pythonhosted.org/packages/c7/b1/19008d060d4a8216b7cbf279b200cf97f41bd3b209f4eb63656ababbe2e2/dbg_print_tool-1.0.9-py3-none-any.whl",
        "yanked": false,
        "yanked_reason": null
      },
      {
        "comment_text": "",
        "digests": {
          "blake2b_256": "823a1df836fd7b6c5594b6c5d17eab5a4f2a3108277f1fb0eaf03e7c187d3f3f",
          "md5": "baab600e971b13e14e83aca5c8ab744f",
          "sha256": "487bf3fab32970cd0beb99ef3bdfc9fa719c2401c4e4dde6a6236640ffb11949"
        },
        "downloads": -1,
        "filename": "dbg-print-tool-1.0.9.tar.gz",
        "has_sig": false,
        "md5_digest": "baab600e971b13e14e83aca5c8ab744f",
        "packagetype": "sdist",
        "python_version": "source",
        "requires_python": ">=3.8",
        "size": 2083,
        "upload_time": "2022-12-17T21:24:21",
        "upload_time_iso_8601": "2022-12-17T21:24:21.765565Z",
        "url": "https://files.pythonhosted.org/packages/82/3a/1df836fd7b6c5594b6c5d17eab5a4f2a3108277f1fb0eaf03e7c187d3f3f/dbg-print-tool-1.0.9.tar.gz",
        "yanked": false,
        "yanked_reason": null
      }
    ]
  },
  "urls": [
    {
      "comment_text": "",
      "digests": {
        "blake2b_256": "847497fe04d869e399fea2cd2cd63faa07a3a8e7a69773951f9c48118e565c25",
        "md5": "f0816934c34da960a220ca9052c8f94d",
        "sha256": "c7292d4fc6e7188dd03cd29b762afc5af6de1e48203b859d2a2b66551fed41fc"
      },
      "downloads": -1,
      "filename": "dbg_print_tool-1.0.22-py3-none-any.whl",
      "has_sig": false,
      "md5_digest": "f0816934c34da960a220ca9052c8f94d",
      "packagetype": "bdist_wheel",
      "python_version": "py3",
      "requires_python": ">=3.8",
      "size": 2714,
      "upload_time": "2022-12-18T01:09:16",
      "upload_time_iso_8601": "2022-12-18T01:09:16.448280Z",
      "url": "https://files.pythonhosted.org/packages/84/74/97fe04d869e399fea2cd2cd63faa07a3a8e7a69773951f9c48118e565c25/dbg_print_tool-1.0.22-py3-none-any.whl",
      "yanked": false,
      "yanked_reason": null
    },
    {
      "comment_text": "",
      "digests": {
        "blake2b_256": "5cff8045e3b23224a7a5a35fcd9db1cf19c587166103dc366637f972ee551587",
        "md5": "0a746911390ea473c1d410aab6b28079",
        "sha256": "a6027ca665a6b39e717c1d42954a3515d3fd895aab66680391a02c3335ca395f"
      },
      "downloads": -1,
      "filename": "dbg-print-tool-1.0.22.tar.gz",
      "has_sig": false,
      "md5_digest": "0a746911390ea473c1d410aab6b28079",
      "packagetype": "sdist",
      "python_version": "source",
      "requires_python": ">=3.8",
      "size": 2234,
      "upload_time": "2022-12-18T01:09:17",
      "upload_time_iso_8601": "2022-12-18T01:09:17.606270Z",
      "url": "https://files.pythonhosted.org/packages/5c/ff/8045e3b23224a7a5a35fcd9db1cf19c587166103dc366637f972ee551587/dbg-print-tool-1.0.22.tar.gz",
      "yanked": false,
      "yanked_reason": null
    }
  ],
  "vulnerabilities": []
}