{
  "info": {
    "author": "Christian Marzahl",
    "author_email": "christian.marzahl@gamil.com",
    "bugtrack_url": null,
    "classifiers": [
      "License :: OSI Approved :: MIT License",
      "Operating System :: OS Independent",
      "Programming Language :: Python :: 3"
    ],
    "description": "# EXACT-Sync\n\n[![PyPI version fury.io](https://badge.fury.io/py/EXCAT-Sync.svg)](https://pypi.python.org/pypi/EXCAT-Sync/)\n[![MIT license](https://img.shields.io/badge/License-MIT-blue.svg)](https://lbesson.mit-license.org/)\n\n\n\nRest API sync with the EXACT Server https://github.com/ChristianMarzahl/Exact\n\n[Browsable-API](https://documenter.getpostman.com/view/11308910/TVYF6xZo)\n\n## Example Notebooks\n\nIn the folder examples\n\n## Pip\n\npip install EXCAT-Sync\n\n## Tests\n\nwith a lot of implementation examples\n/exact_sync/v1/test\n\n\n### Basic features:\n\n#### Connect to server\n\n```python\nconfiguration = Configuration()\nconfiguration.username = 'exact'\nconfiguration.password = 'exact'\nconfiguration.host = \"http://127.0.0.1:8000\"\n\nclient = ApiClient(configuration)\n\nimage_sets_api = ImageSetsApi(client)\nannotations_api = AnnotationsApi(client)\nannotation_types_api = AnnotationTypesApi(client)\nimages_api = ImagesApi(client)\nproduct_api = ProductsApi(client)\nteam_api = TeamsApi(client)\n```\n\n\n#### Get image set information\n```python\nimage_sets = image_sets_api.list_image_sets(name=\"cluster_asthma_imageset\")\nimage_sets\n```\n\n#### Upload image to image set\n\n```python\nimage_type = int(Image.ImageSourceTypes.DEFAULT)\nimage = images_api.create_image(file_path=target_file, image_type=image_type, image_set=image_set.id).results[0]\n```\n\n##### Donwload image from image set\n\n```python\nimages_api.download_image(id=image_id, target_path=image_path, original_image=True)\n```\n\n#### Download image annotations \n\n```python\nannotations_api.list_annotations(pagination=False, async_req=True, image=image.id)\n```\n\n\n",
    "description_content_type": "text/markdown",
    "docs_url": null,
    "download_url": "",
    "downloads": {
      "last_day": -1,
      "last_month": -1,
      "last_week": -1
    },
    "home_page": "https://github.com/ChristianMarzahl/EXACT-Sync",
    "keywords": "",
    "license": "",
    "maintainer": "",
    "maintainer_email": "",
    "name": "EXCAT-Sync",
    "package_url": "https://pypi.org/project/EXCAT-Sync/",
    "platform": null,
    "project_url": "https://pypi.org/project/EXCAT-Sync/",
    "project_urls": {
      "Homepage": "https://github.com/ChristianMarzahl/EXACT-Sync"
    },
    "release_url": "https://pypi.org/project/EXCAT-Sync/0.0.38/",
    "requires_dist": [
      "requests",
      "tqdm",
      "requests-toolbelt",
      "pillow",
      "locust (==1.1.0)"
    ],
    "requires_python": ">=3.6",
    "summary": "A package to download images and annotations from the EXACT Server https://github.com/ChristianMarzahl/Exact",
    "version": "0.0.38",
    "yanked": false,
    "yanked_reason": null
  },
  "last_serial": 17456790,
  "releases": {
    "0.0.1": [
      {
        "comment_text": "",
        "digests": {
          "blake2b_256": "ee3b2b08fbcca396cf01fee263a93f582a70e72a63b1f03468b1416263c0c71a",
          "md5": "4b37fca1693617277f237bd592605c2a",
          "sha256": "ec2ca26bcc4adf47de640768ed5c9b1ceff18223bad37fd2a35c751480139b09"
        },
        "downloads": -1,
        "filename": "EXCAT_Sync-0.0.1-py3-none-any.whl",
        "has_sig": false,
        "md5_digest": "4b37fca1693617277f237bd592605c2a",
        "packagetype": "bdist_wheel",
        "python_version": "py3",
        "requires_python": ">=3.6",
        "size": 4971,
        "upload_time": "2020-02-24T12:53:39",
        "upload_time_iso_8601": "2020-02-24T12:53:39.176611Z",
        "url": "https://files.pythonhosted.org/packages/ee/3b/2b08fbcca396cf01fee263a93f582a70e72a63b1f03468b1416263c0c71a/EXCAT_Sync-0.0.1-py3-none-any.whl",
        "yanked": false,
        "yanked_reason": null
      },
      {
        "comment_text": "",
        "digests": {
          "blake2b_256": "ff89a09c129d6d48afc582eb3c902ef9791729e922cf250b6cf6f1fa35cb758c",
          "md5": "c552bf83b5101a04f10b47acfd5fb112",
          "sha256": "2d9d8bff9e074489d94f8d0aca3571caab671e38c38cee2b2bf152a1bc76e92c"
        },
        "downloads": -1,
        "filename": "EXCAT-Sync-0.0.1.tar.gz",
        "has_sig": false,
        "md5_digest": "c552bf83b5101a04f10b47acfd5fb112",
        "packagetype": "sdist",
        "python_version": "source",
        "requires_python": ">=3.6",
        "size": 3253,
        "upload_time": "2020-02-24T12:53:42",
        "upload_time_iso_8601": "2020-02-24T12:53:42.967728Z",
        "url": "https://files.pythonhosted.org/packages/ff/89/a09c129d6d48afc582eb3c902ef9791729e922cf250b6cf6f1fa35cb758c/EXCAT-Sync-0.0.1.tar.gz",
        "yanked": false,
        "yanked_reason": null
      }
    ],
    "0.0.10": [
      {
        "comment_text": "",
        "digests": {
          "blake2b_256": "59528457a3ed42190d63c1e0adcd46eeef0446a458e8618f92efe4c27bd7ec6f",
          "md5": "d168497d17d8fc6e26c611505f5ed12d",
          "sha256": "79e11ece4e0fc1de66b6e58ea0a15057c8189743aa24563a568549c22fc2f53f"
        },
        "downloads": -1,
        "filename": "EXCAT_Sync-0.0.10-py3-none-any.whl",
        "has_sig": false,
        "md5_digest": "d168497d17d8fc6e26c611505f5ed12d",
        "packagetype": "bdist_wheel",
        "python_version": "py3",
        "requires_python": ">=3.6",
        "size": 113974,
        "upload_time": "2020-04-24T14:06:49",
        "upload_time_iso_8601": "2020-04-24T14:06:49.621013Z",
        "url": "https://files.pythonhosted.org/packages/59/52/8457a3ed42190d63c1e0adcd46eeef0446a458e8618f92efe4c27bd7ec6f/EXCAT_Sync-0.0.10-py3-none-any.whl",
        "yanked": false,
        "yanked_reason": null
      },
      {
        "comment_text": "",
        "digests": {
          "blake2b_256": "6590e245e2f9c6d8485bf99c9d46f35eb78d8dbecdb348d59f79c659d0216e00",
          "md5": "5b422c481f2345339cce157b8c24bb89",
          "sha256": "29f0fcf72c4653a739acd8a519017973985cd7ddc3e922297fe5f869ef017d64"
        },
        "downloads": -1,
        "filename": "EXCAT-Sync-0.0.10.tar.gz",
        "has_sig": false,
        "md5_digest": "5b422c481f2345339cce157b8c24bb89",
        "packagetype": "sdist",
        "python_version": "source",
        "requires_python": ">=3.6",
        "size": 52901,
        "upload_time": "2020-04-24T14:06:53",
        "upload_time_iso_8601": "2020-04-24T14:06:53.456096Z",
        "url": "https://files.pythonhosted.org/packages/65/90/e245e2f9c6d8485bf99c9d46f35eb78d8dbecdb348d59f79c659d0216e00/EXCAT-Sync-0.0.10.tar.gz",
        "yanked": false,
        "yanked_reason": null
      }
    ],
    "0.0.11": [
      {
        "comment_text": "",
        "digests": {
          "blake2b_256": "3b78562881b893c47ebaa0b886711cc1ea5ed11b59846dc4443aa0de8470a687",
          "md5": "a6eebad30696a6531197f9ce4795fe9b",
          "sha256": "6e2930ca42cf6a35aae542fdaf0596b3b50a6f123161e4fb9b3ee09c6ca02fa0"
        },
        "downloads": -1,
        "filename": "EXCAT_Sync-0.0.11-py3-none-any.whl",
        "has_sig": false,
        "md5_digest": "a6eebad30696a6531197f9ce4795fe9b",
        "packagetype": "bdist_wheel",
        "python_version": "py3",
        "requires_python": ">=3.6",
        "size": 114069,
        "upload_time": "2020-05-02T14:58:40",
        "upload_time_iso_8601": "2020-05-02T14:58:40.693864Z",
        "url": "https://files.pythonhosted.org/packages/3b/78/562881b893c47ebaa0b886711cc1ea5ed11b59846dc4443aa0de8470a687/EXCAT_Sync-0.0.11-py3-none-any.whl",
        "yanked": false,
        "yanked_reason": null
      },
      {
        "comment_text": "",
        "digests": {
          "blake2b_256": "7a91ea018fc68e41ac5a3645d8892fe06673f077681257503ee5d0cb6e608044",
          "md5": "da41db6594be515ae1925d0477c7932a",
          "sha256": "98590f22e69224a121a71029161b293de409645e8e11dc6fe175db6920a2e57b"
        },
        "downloads": -1,
        "filename": "EXCAT-Sync-0.0.11.tar.gz",
        "has_sig": false,
        "md5_digest": "da41db6594be515ae1925d0477c7932a",
        "packagetype": "sdist",
        "python_version": "source",
        "requires_python": ">=3.6",
        "size": 52998,
        "upload_time": "2020-05-02T14:58:46",
        "upload_time_iso_8601": "2020-05-02T14:58:46.080839Z",
        "url": "https://files.pythonhosted.org/packages/7a/91/ea018fc68e41ac5a3645d8892fe06673f077681257503ee5d0cb6e608044/EXCAT-Sync-0.0.11.tar.gz",
        "yanked": false,
        "yanked_reason": null
      }
    ],
    "0.0.12": [
      {
        "comment_text": "",
        "digests": {
          "blake2b_256": "2fd67c57db900a7ade03822c92826fc95b3d4cb78a8e11e5ee1461fa78c812db",
          "md5": "8387d2d0c3791336cf8343b699ff75d9",
          "sha256": "d6aa8011904b8f414721c9d3bbe11debe7972f7262473e46a6252f4435bcc966"
        },
        "downloads": -1,
        "filename": "EXCAT_Sync-0.0.12-py3-none-any.whl",
        "has_sig": false,
        "md5_digest": "8387d2d0c3791336cf8343b699ff75d9",
        "packagetype": "bdist_wheel",
        "python_version": "py3",
        "requires_python": ">=3.6",
        "size": 114154,
        "upload_time": "2020-05-06T13:49:28",
        "upload_time_iso_8601": "2020-05-06T13:49:28.449057Z",
        "url": "https://files.pythonhosted.org/packages/2f/d6/7c57db900a7ade03822c92826fc95b3d4cb78a8e11e5ee1461fa78c812db/EXCAT_Sync-0.0.12-py3-none-any.whl",
        "yanked": false,
        "yanked_reason": null
      },
      {
        "comment_text": "",
        "digests": {
          "blake2b_256": "40b94fb5c4d333ca15df2c7e29d6549c13ac014a17a31a04b963d0a0bebfd20f",
          "md5": "042993d94056af3e671e17c12aa13c97",
          "sha256": "0398c9e003752403452078cdc420903cfc8a271b7688e7bad0b9d72cdeed33f9"
        },
        "downloads": -1,
        "filename": "EXCAT-Sync-0.0.12.tar.gz",
        "has_sig": false,
        "md5_digest": "042993d94056af3e671e17c12aa13c97",
        "packagetype": "sdist",
        "python_version": "source",
        "requires_python": ">=3.6",
        "size": 53106,
        "upload_time": "2020-05-06T13:49:33",
        "upload_time_iso_8601": "2020-05-06T13:49:33.630946Z",
        "url": "https://files.pythonhosted.org/packages/40/b9/4fb5c4d333ca15df2c7e29d6549c13ac014a17a31a04b963d0a0bebfd20f/EXCAT-Sync-0.0.12.tar.gz",
        "yanked": false,
        "yanked_reason": null
      }
    ],
    "0.0.13": [
      {
        "comment_text": "",
        "digests": {
          "blake2b_256": "729fff7599a9053f476e3d7b22b630bfc9851fcbbfc34d41110b1c014e884336",
          "md5": "a70ce8a42a03d09ea0ecb1b09f520963",
          "sha256": "3a8ff07038097d9715149ed2eadd26623af9b5e309c5e3edfb23cdf13ed3b587"
        },
        "downloads": -1,
        "filename": "EXCAT_Sync-0.0.13-py3-none-any.whl",
        "has_sig": false,
        "md5_digest": "a70ce8a42a03d09ea0ecb1b09f520963",
        "packagetype": "bdist_wheel",
        "python_version": "py3",
        "requires_python": ">=3.6",
        "size": 114218,
        "upload_time": "2020-05-13T12:10:28",
        "upload_time_iso_8601": "2020-05-13T12:10:28.988810Z",
        "url": "https://files.pythonhosted.org/packages/72/9f/ff7599a9053f476e3d7b22b630bfc9851fcbbfc34d41110b1c014e884336/EXCAT_Sync-0.0.13-py3-none-any.whl",
        "yanked": false,
        "yanked_reason": null
      },
      {
        "comment_text": "",
        "digests": {
          "blake2b_256": "c04054fa47dbce25e1cfef7e7e13d61d35f644119e6d73d2398b85ce9fddabc4",
          "md5": "5f10861dc88db0e22c768babbdcc7b0f",
          "sha256": "eb3efd80099d041018c5497b295de8376bfbae1c702260ce7358a3985d4e3af3"
        },
        "downloads": -1,
        "filename": "EXCAT-Sync-0.0.13.tar.gz",
        "has_sig": false,
        "md5_digest": "5f10861dc88db0e22c768babbdcc7b0f",
        "packagetype": "sdist",
        "python_version": "source",
        "requires_python": ">=3.6",
        "size": 53244,
        "upload_time": "2020-05-13T12:10:34",
        "upload_time_iso_8601": "2020-05-13T12:10:34.617962Z",
        "url": "https://files.pythonhosted.org/packages/c0/40/54fa47dbce25e1cfef7e7e13d61d35f644119e6d73d2398b85ce9fddabc4/EXCAT-Sync-0.0.13.tar.gz",
        "yanked": false,
        "yanked_reason": null
      }
    ],
    "0.0.14": [
      {
        "comment_text": "",
        "digests": {
          "blake2b_256": "041f76521d911492015fdfa51f842ebb67ddda4edff5bf8562e0046d04a739ce",
          "md5": "29003a5902132076bcbf6eb4045404bf",
          "sha256": "88fd6ed3b5a3d5fbd7e233f14643dbb6b1ea1e355b991a58f7fda13a7bbaa208"
        },
        "downloads": -1,
        "filename": "EXCAT_Sync-0.0.14-py3-none-any.whl",
        "has_sig": false,
        "md5_digest": "29003a5902132076bcbf6eb4045404bf",
        "packagetype": "bdist_wheel",
        "python_version": "py3",
        "requires_python": ">=3.6",
        "size": 114751,
        "upload_time": "2020-07-23T14:29:30",
        "upload_time_iso_8601": "2020-07-23T14:29:30.740235Z",
        "url": "https://files.pythonhosted.org/packages/04/1f/76521d911492015fdfa51f842ebb67ddda4edff5bf8562e0046d04a739ce/EXCAT_Sync-0.0.14-py3-none-any.whl",
        "yanked": false,
        "yanked_reason": null
      },
      {
        "comment_text": "",
        "digests": {
          "blake2b_256": "756e7e22b6fb9406bbb39e075c9e7528ff905ffee32243e9c7ced525bee0e8fa",
          "md5": "bd8752b7fe205573af822c119195c9df",
          "sha256": "97d9fe16e2563034a6a96ce2c50ef032225308672d6959392c8a02e77537ba06"
        },
        "downloads": -1,
        "filename": "EXCAT-Sync-0.0.14.tar.gz",
        "has_sig": false,
        "md5_digest": "bd8752b7fe205573af822c119195c9df",
        "packagetype": "sdist",
        "python_version": "source",
        "requires_python": ">=3.6",
        "size": 53553,
        "upload_time": "2020-07-23T14:29:37",
        "upload_time_iso_8601": "2020-07-23T14:29:37.458412Z",
        "url": "https://files.pythonhosted.org/packages/75/6e/7e22b6fb9406bbb39e075c9e7528ff905ffee32243e9c7ced525bee0e8fa/EXCAT-Sync-0.0.14.tar.gz",
        "yanked": false,
        "yanked_reason": null
      }
    ],
    "0.0.15": [
      {
        "comment_text": "",
        "digests": {
          "blake2b_256": "d1070fbc0038542965d2e3f38a258b38d6ca8d4d86023fb17da75d2605820f0d",
          "md5": "d04588b3a803249f62bc298f3dfa8e9a",
          "sha256": "1301b118a60a610f5f0f0cf1c7cac8f92f4d859b6dbb5e23afd921a88c29a3f4"
        },
        "downloads": -1,
        "filename": "EXCAT_Sync-0.0.15-py3-none-any.whl",
        "has_sig": false,
        "md5_digest": "d04588b3a803249f62bc298f3dfa8e9a",
        "packagetype": "bdist_wheel",
        "python_version": "py3",
        "requires_python": ">=3.6",
        "size": 115005,
        "upload_time": "2020-07-26T14:35:27",
        "upload_time_iso_8601": "2020-07-26T14:35:27.030777Z",
        "url": "https://files.pythonhosted.org/packages/d1/07/0fbc0038542965d2e3f38a258b38d6ca8d4d86023fb17da75d2605820f0d/EXCAT_Sync-0.0.15-py3-none-any.whl",
        "yanked": false,
        "yanked_reason": null
      },
      {
        "comment_text": "",
        "digests": {
          "blake2b_256": "895823f91512c2052636de915271f41d76d7009fa77f13ec97f1aa97cb5b4555",
          "md5": "32e1e3afebc8be67382037c30458bb74",
          "sha256": "1bd891e09e6137610954af601595b643f008e7057541670d0dc9df5cebb2042d"
        },
        "downloads": -1,
        "filename": "EXCAT-Sync-0.0.15.tar.gz",
        "has_sig": false,
        "md5_digest": "32e1e3afebc8be67382037c30458bb74",
        "packagetype": "sdist",
        "python_version": "source",
        "requires_python": ">=3.6",
        "size": 53791,
        "upload_time": "2020-07-26T14:35:35",
        "upload_time_iso_8601": "2020-07-26T14:35:35.948541Z",
        "url": "https://files.pythonhosted.org/packages/89/58/23f91512c2052636de915271f41d76d7009fa77f13ec97f1aa97cb5b4555/EXCAT-Sync-0.0.15.tar.gz",
        "yanked": false,
        "yanked_reason": null
      }
    ],
    "0.0.16": [
      {
        "comment_text": "",
        "digests": {
          "blake2b_256": "235d189cc661ac50665f203d725c6aa9f58cb6d38dc9a708b3e1f1534afe3a0b",
          "md5": "0a0aad83e57b0419c01cd2a92fea439a",
          "sha256": "127370028df475a3012462804f69bd9fe6a3f9d13af98fa5d1481b98f63209b7"
        },
        "downloads": -1,
        "filename": "EXCAT_Sync-0.0.16-py3-none-any.whl",
        "has_sig": false,
        "md5_digest": "0a0aad83e57b0419c01cd2a92fea439a",
        "packagetype": "bdist_wheel",
        "python_version": "py3",
        "requires_python": ">=3.6",
        "size": 115059,
        "upload_time": "2020-07-27T07:03:16",
        "upload_time_iso_8601": "2020-07-27T07:03:16.465822Z",
        "url": "https://files.pythonhosted.org/packages/23/5d/189cc661ac50665f203d725c6aa9f58cb6d38dc9a708b3e1f1534afe3a0b/EXCAT_Sync-0.0.16-py3-none-any.whl",
        "yanked": false,
        "yanked_reason": null
      },
      {
        "comment_text": "",
        "digests": {
          "blake2b_256": "dcc47279a9bc02223eddb66c2f19c2972a3cd73f14c3a14395ece52f1eeaa55f",
          "md5": "50d31f347c861323a9f02ad656031276",
          "sha256": "521db1ddbc3c96ecf0ca62f9332a42b94a57f8bee7a39fd4accbccf032b62e6c"
        },
        "downloads": -1,
        "filename": "EXCAT-Sync-0.0.16.tar.gz",
        "has_sig": false,
        "md5_digest": "50d31f347c861323a9f02ad656031276",
        "packagetype": "sdist",
        "python_version": "source",
        "requires_python": ">=3.6",
        "size": 54897,
        "upload_time": "2020-07-27T07:03:23",
        "upload_time_iso_8601": "2020-07-27T07:03:23.376688Z",
        "url": "https://files.pythonhosted.org/packages/dc/c4/7279a9bc02223eddb66c2f19c2972a3cd73f14c3a14395ece52f1eeaa55f/EXCAT-Sync-0.0.16.tar.gz",
        "yanked": false,
        "yanked_reason": null
      }
    ],
    "0.0.17": [
      {
        "comment_text": "",
        "digests": {
          "blake2b_256": "212288ea258b98769879ae4a4d717ee02a6cd622bfc81fcd29434d79efa7c355",
          "md5": "99b0bd5af6890fb75ce8fdd85964b88c",
          "sha256": "cd1630b27acd77804cd04cbdd7568d41c6f5b937d75f984b1d9b28d6cd5b3193"
        },
        "downloads": -1,
        "filename": "EXCAT_Sync-0.0.17-py3-none-any.whl",
        "has_sig": false,
        "md5_digest": "99b0bd5af6890fb75ce8fdd85964b88c",
        "packagetype": "bdist_wheel",
        "python_version": "py3",
        "requires_python": ">=3.6",
        "size": 115103,
        "upload_time": "2020-07-27T11:53:48",
        "upload_time_iso_8601": "2020-07-27T11:53:48.786782Z",
        "url": "https://files.pythonhosted.org/packages/21/22/88ea258b98769879ae4a4d717ee02a6cd622bfc81fcd29434d79efa7c355/EXCAT_Sync-0.0.17-py3-none-any.whl",
        "yanked": false,
        "yanked_reason": null
      },
      {
        "comment_text": "",
        "digests": {
          "blake2b_256": "ba97bce6dcd0ed077a1b705c3af2e873cd5ba3766b59e92aec572d4572f31e27",
          "md5": "9ecdb3ae3cf07a6bfe4320957583731a",
          "sha256": "24e003d0ffbf480bec67d322756c7424046570e7bcfbac8c147c092b6fae6dbc"
        },
        "downloads": -1,
        "filename": "EXCAT-Sync-0.0.17.tar.gz",
        "has_sig": false,
        "md5_digest": "9ecdb3ae3cf07a6bfe4320957583731a",
        "packagetype": "sdist",
        "python_version": "source",
        "requires_python": ">=3.6",
        "size": 54929,
        "upload_time": "2020-07-27T11:53:59",
        "upload_time_iso_8601": "2020-07-27T11:53:59.644840Z",
        "url": "https://files.pythonhosted.org/packages/ba/97/bce6dcd0ed077a1b705c3af2e873cd5ba3766b59e92aec572d4572f31e27/EXCAT-Sync-0.0.17.tar.gz",
        "yanked": false,
        "yanked_reason": null
      }
    ],
    "0.0.18": [
      {
        "comment_text": "",
        "digests": {
          "blake2b_256": "8a5d84d9174417b3d067a04ed44306ed86a7d6cd8986e030b40d29935bb32716",
          "md5": "1285221568c883cb136ee669e7e6d857",
          "sha256": "b0e10455b1ebbf73ae5859f237d0dd64ade0cce414af6e9c99f6aba8b0aacc5b"
        },
        "downloads": -1,
        "filename": "EXCAT_Sync-0.0.18-py3-none-any.whl",
        "has_sig": false,
        "md5_digest": "1285221568c883cb136ee669e7e6d857",
        "packagetype": "bdist_wheel",
        "python_version": "py3",
        "requires_python": ">=3.6",
        "size": 116988,
        "upload_time": "2020-08-20T19:58:27",
        "upload_time_iso_8601": "2020-08-20T19:58:27.268442Z",
        "url": "https://files.pythonhosted.org/packages/8a/5d/84d9174417b3d067a04ed44306ed86a7d6cd8986e030b40d29935bb32716/EXCAT_Sync-0.0.18-py3-none-any.whl",
        "yanked": false,
        "yanked_reason": null
      },
      {
        "comment_text": "",
        "digests": {
          "blake2b_256": "908d1fcb050ae3b2dbdf66727f8fba420ae7c08512ae521010b35e2ceb9b752f",
          "md5": "b3f8755f669fb141af7b02421a9973b8",
          "sha256": "f2b99cce20d53ae2b7cbfbc2330b0332f5707277d00cc7f1fb22df5f4498181c"
        },
        "downloads": -1,
        "filename": "EXCAT-Sync-0.0.18.tar.gz",
        "has_sig": false,
        "md5_digest": "b3f8755f669fb141af7b02421a9973b8",
        "packagetype": "sdist",
        "python_version": "source",
        "requires_python": ">=3.6",
        "size": 55841,
        "upload_time": "2020-08-20T19:58:37",
        "upload_time_iso_8601": "2020-08-20T19:58:37.373226Z",
        "url": "https://files.pythonhosted.org/packages/90/8d/1fcb050ae3b2dbdf66727f8fba420ae7c08512ae521010b35e2ceb9b752f/EXCAT-Sync-0.0.18.tar.gz",
        "yanked": false,
        "yanked_reason": null
      }
    ],
    "0.0.19": [
      {
        "comment_text": "",
        "digests": {
          "blake2b_256": "ecc3f40684565c5622479f37f5df6568caa7d49e2ec7d9c368afc6d821f212b5",
          "md5": "b196d4cf861a3452744ea66a433fe7ba",
          "sha256": "be46f7e47cbcd6ce47a20c1779c2a4d79ec3657033d2184f0a662f8e6432cb48"
        },
        "downloads": -1,
        "filename": "EXCAT_Sync-0.0.19-py3-none-any.whl",
        "has_sig": false,
        "md5_digest": "b196d4cf861a3452744ea66a433fe7ba",
        "packagetype": "bdist_wheel",
        "python_version": "py3",
        "requires_python": ">=3.6",
        "size": 117098,
        "upload_time": "2020-09-15T12:58:24",
        "upload_time_iso_8601": "2020-09-15T12:58:24.021494Z",
        "url": "https://files.pythonhosted.org/packages/ec/c3/f40684565c5622479f37f5df6568caa7d49e2ec7d9c368afc6d821f212b5/EXCAT_Sync-0.0.19-py3-none-any.whl",
        "yanked": false,
        "yanked_reason": null
      },
      {
        "comment_text": "",
        "digests": {
          "blake2b_256": "30a625ffb0b0ec7b0ff3776763037faf5905860dd307f253cbd37e0c1e1ff3a3",
          "md5": "1343d379e28d0b8c96cb451c77eb72f5",
          "sha256": "9ef5d1970d0a85011f474e3be6fb5ba2ed06dd4ff51fa68b76521d72b8d0cc6b"
        },
        "downloads": -1,
        "filename": "EXCAT-Sync-0.0.19.tar.gz",
        "has_sig": false,
        "md5_digest": "1343d379e28d0b8c96cb451c77eb72f5",
        "packagetype": "sdist",
        "python_version": "source",
        "requires_python": ">=3.6",
        "size": 55946,
        "upload_time": "2020-09-15T12:58:32",
        "upload_time_iso_8601": "2020-09-15T12:58:32.966434Z",
        "url": "https://files.pythonhosted.org/packages/30/a6/25ffb0b0ec7b0ff3776763037faf5905860dd307f253cbd37e0c1e1ff3a3/EXCAT-Sync-0.0.19.tar.gz",
        "yanked": false,
        "yanked_reason": null
      }
    ],
    "0.0.2": [
      {
        "comment_text": "",
        "digests": {
          "blake2b_256": "7b2dd74fe13dd51995be2126bd7be2b300dca7eacf076bc2eab6254ba4a54c6a",
          "md5": "bdcd2a9e17c90fefa15aa5d0f739e062",
          "sha256": "7a8773d24c6eb9305c68ebb0dcd2c1379d268cc50074dd0f3182cd782a286cd8"
        },
        "downloads": -1,
        "filename": "EXCAT_Sync-0.0.2-py3-none-any.whl",
        "has_sig": false,
        "md5_digest": "bdcd2a9e17c90fefa15aa5d0f739e062",
        "packagetype": "bdist_wheel",
        "python_version": "py3",
        "requires_python": ">=3.6",
        "size": 5067,
        "upload_time": "2020-02-24T12:53:41",
        "upload_time_iso_8601": "2020-02-24T12:53:41.427412Z",
        "url": "https://files.pythonhosted.org/packages/7b/2d/d74fe13dd51995be2126bd7be2b300dca7eacf076bc2eab6254ba4a54c6a/EXCAT_Sync-0.0.2-py3-none-any.whl",
        "yanked": false,
        "yanked_reason": null
      },
      {
        "comment_text": "",
        "digests": {
          "blake2b_256": "da7d4b09dc408fa9c3dc40f9a3afa75588fc53e3bd8ba11308d9cc3d85fc0653",
          "md5": "a8b16e631187d68b52abe525f94a3443",
          "sha256": "f2fc0a95aecb326abdeb3d339fe496a165e9f04310aa201f2a663f948422da4e"
        },
        "downloads": -1,
        "filename": "EXCAT-Sync-0.0.2.tar.gz",
        "has_sig": false,
        "md5_digest": "a8b16e631187d68b52abe525f94a3443",
        "packagetype": "sdist",
        "python_version": "source",
        "requires_python": ">=3.6",
        "size": 3384,
        "upload_time": "2020-02-24T12:53:44",
        "upload_time_iso_8601": "2020-02-24T12:53:44.314696Z",
        "url": "https://files.pythonhosted.org/packages/da/7d/4b09dc408fa9c3dc40f9a3afa75588fc53e3bd8ba11308d9cc3d85fc0653/EXCAT-Sync-0.0.2.tar.gz",
        "yanked": false,
        "yanked_reason": null
      }
    ],
    "0.0.20": [
      {
        "comment_text": "",
        "digests": {
          "blake2b_256": "842dc229062617be4b8f3c157e8d27e3abd2975c90fd0a545fc54bbcc1f32663",
          "md5": "0d887be39fef106b3e5b4e869e00e1d3",
          "sha256": "5beef1f2bb1799acd310094ba9d782f6ac1f7b8b053e101d90f332ee3721f282"
        },
        "downloads": -1,
        "filename": "EXCAT_Sync-0.0.20-py3-none-any.whl",
        "has_sig": false,
        "md5_digest": "0d887be39fef106b3e5b4e869e00e1d3",
        "packagetype": "bdist_wheel",
        "python_version": "py3",
        "requires_python": ">=3.6",
        "size": 117121,
        "upload_time": "2020-09-17T09:10:05",
        "upload_time_iso_8601": "2020-09-17T09:10:05.310206Z",
        "url": "https://files.pythonhosted.org/packages/84/2d/c229062617be4b8f3c157e8d27e3abd2975c90fd0a545fc54bbcc1f32663/EXCAT_Sync-0.0.20-py3-none-any.whl",
        "yanked": false,
        "yanked_reason": null
      },
      {
        "comment_text": "",
        "digests": {
          "blake2b_256": "23a210f293fa8cf423af55362386915eff2e18614bec3a695adbeae830887014",
          "md5": "313e79a7a033edef71118da48da7d902",
          "sha256": "cae683d15a1694980f50c973bd5acd6873f5b095533812f40a0314ff99502c96"
        },
        "downloads": -1,
        "filename": "EXCAT-Sync-0.0.20.tar.gz",
        "has_sig": false,
        "md5_digest": "313e79a7a033edef71118da48da7d902",
        "packagetype": "sdist",
        "python_version": "source",
        "requires_python": ">=3.6",
        "size": 55957,
        "upload_time": "2020-09-17T09:10:16",
        "upload_time_iso_8601": "2020-09-17T09:10:16.435928Z",
        "url": "https://files.pythonhosted.org/packages/23/a2/10f293fa8cf423af55362386915eff2e18614bec3a695adbeae830887014/EXCAT-Sync-0.0.20.tar.gz",
        "yanked": false,
        "yanked_reason": null
      }
    ],
    "0.0.21": [
      {
        "comment_text": "",
        "digests": {
          "blake2b_256": "cc553f7370a074cd0cf4c753b5de8de42836811378000aa3a96aaac3d7e53c61",
          "md5": "ea415c9ec0c2efea2817a5b7a98141e9",
          "sha256": "28dc4849aff69f0c03e3f0739f7c4fa16f020a4eaa7e98e14fe909e52a4c2e6e"
        },
        "downloads": -1,
        "filename": "EXCAT_Sync-0.0.21-py3-none-any.whl",
        "has_sig": false,
        "md5_digest": "ea415c9ec0c2efea2817a5b7a98141e9",
        "packagetype": "bdist_wheel",
        "python_version": "py3",
        "requires_python": ">=3.6",
        "size": 125267,
        "upload_time": "2021-03-07T09:17:34",
        "upload_time_iso_8601": "2021-03-07T09:17:34.589700Z",
        "url": "https://files.pythonhosted.org/packages/cc/55/3f7370a074cd0cf4c753b5de8de42836811378000aa3a96aaac3d7e53c61/EXCAT_Sync-0.0.21-py3-none-any.whl",
        "yanked": false,
        "yanked_reason": null
      },
      {
        "comment_text": "",
        "digests": {
          "blake2b_256": "5e48904506436c890b8cdf5ab5ce943f4bc7061fb5f2fb62129059f0f005d40d",
          "md5": "5bebdfe90e7748ac277e4af09b483473",
          "sha256": "48ed2a0164207f634755b9388fc8931b1abe91d81db7f2f550b8dfacb668816a"
        },
        "downloads": -1,
        "filename": "EXCAT-Sync-0.0.21.tar.gz",
        "has_sig": false,
        "md5_digest": "5bebdfe90e7748ac277e4af09b483473",
        "packagetype": "sdist",
        "python_version": "source",
        "requires_python": ">=3.6",
        "size": 59859,
        "upload_time": "2021-03-07T09:17:50",
        "upload_time_iso_8601": "2021-03-07T09:17:50.068111Z",
        "url": "https://files.pythonhosted.org/packages/5e/48/904506436c890b8cdf5ab5ce943f4bc7061fb5f2fb62129059f0f005d40d/EXCAT-Sync-0.0.21.tar.gz",
        "yanked": false,
        "yanked_reason": null
      }
    ],
    "0.0.22": [
      {
        "comment_text": "",
        "digests": {
          "blake2b_256": "4acd87a9b52ac9e7ab82c83ef79ae112a75b7c47e7eb0edd572797c4051dfdc8",
          "md5": "4f4a68f62b2cfe70d449cb7826b0db27",
          "sha256": "75902a311bb0f199eb84900f4a80132f0a6c13fccc171c58b21d72faee4993c3"
        },
        "downloads": -1,
        "filename": "EXCAT_Sync-0.0.22-py3-none-any.whl",
        "has_sig": false,
        "md5_digest": "4f4a68f62b2cfe70d449cb7826b0db27",
        "packagetype": "bdist_wheel",
        "python_version": "py3",
        "requires_python": ">=3.6",
        "size": 125336,
        "upload_time": "2021-03-07T10:13:11",
        "upload_time_iso_8601": "2021-03-07T10:13:11.645236Z",
        "url": "https://files.pythonhosted.org/packages/4a/cd/87a9b52ac9e7ab82c83ef79ae112a75b7c47e7eb0edd572797c4051dfdc8/EXCAT_Sync-0.0.22-py3-none-any.whl",
        "yanked": false,
        "yanked_reason": null
      },
      {
        "comment_text": "",
        "digests": {
          "blake2b_256": "1fdd82c7e59482459c0959809db532aa91a81b8df655b31d1a64b7bc5c2e045b",
          "md5": "ac39f10d097960b4fc7a1c892fd0c46d",
          "sha256": "56af99dea80a3c539a4e05861c92b190adc6a58d987454b5f318b50f90d928ab"
        },
        "downloads": -1,
        "filename": "EXCAT-Sync-0.0.22.tar.gz",
        "has_sig": false,
        "md5_digest": "ac39f10d097960b4fc7a1c892fd0c46d",
        "packagetype": "sdist",
        "python_version": "source",
        "requires_python": ">=3.6",
        "size": 59954,
        "upload_time": "2021-03-07T10:13:26",
        "upload_time_iso_8601": "2021-03-07T10:13:26.924646Z",
        "url": "https://files.pythonhosted.org/packages/1f/dd/82c7e59482459c0959809db532aa91a81b8df655b31d1a64b7bc5c2e045b/EXCAT-Sync-0.0.22.tar.gz",
        "yanked": false,
        "yanked_reason": null
      }
    ],
    "0.0.23": [
      {
        "comment_text": "",
        "digests": {
          "blake2b_256": "25d3746069aa5b4b00d0dd8330f40d3f4bb6a02dccfb12d12e828ba719e4d4cd",
          "md5": "58dcb15ef6c25f436cd60da3a99b3d09",
          "sha256": "4b57913b89e27f861978a46b19c4567b236076e25ff0b5627cc739b91063f9c7"
        },
        "downloads": -1,
        "filename": "EXCAT_Sync-0.0.23-py3-none-any.whl",
        "has_sig": false,
        "md5_digest": "58dcb15ef6c25f436cd60da3a99b3d09",
        "packagetype": "bdist_wheel",
        "python_version": "py3",
        "requires_python": ">=3.6",
        "size": 125739,
        "upload_time": "2021-03-10T08:25:17",
        "upload_time_iso_8601": "2021-03-10T08:25:17.633727Z",
        "url": "https://files.pythonhosted.org/packages/25/d3/746069aa5b4b00d0dd8330f40d3f4bb6a02dccfb12d12e828ba719e4d4cd/EXCAT_Sync-0.0.23-py3-none-any.whl",
        "yanked": false,
        "yanked_reason": null
      },
      {
        "comment_text": "",
        "digests": {
          "blake2b_256": "49d0aebf70cf9eb65bacde625f030c2f869be446adb64e8ce9c8efbf26115670",
          "md5": "e972224105e860a05352a5d7ef5aaf40",
          "sha256": "e525979488a7e63bd5dbbb044c82605aa0a68c87ed3bb8b94fd0e0be809c810c"
        },
        "downloads": -1,
        "filename": "EXCAT-Sync-0.0.23.tar.gz",
        "has_sig": false,
        "md5_digest": "e972224105e860a05352a5d7ef5aaf40",
        "packagetype": "sdist",
        "python_version": "source",
        "requires_python": ">=3.6",
        "size": 60324,
        "upload_time": "2021-03-10T08:25:39",
        "upload_time_iso_8601": "2021-03-10T08:25:39.685315Z",
        "url": "https://files.pythonhosted.org/packages/49/d0/aebf70cf9eb65bacde625f030c2f869be446adb64e8ce9c8efbf26115670/EXCAT-Sync-0.0.23.tar.gz",
        "yanked": false,
        "yanked_reason": null
      }
    ],
    "0.0.24": [
      {
        "comment_text": "",
        "digests": {
          "blake2b_256": "8cfabe6eb5cc18d60049e0f552f6e72dc06b9e366970f8c5efd7b02ed96b6a33",
          "md5": "287a089f6c3d9fbc151a2a74ea496ffa",
          "sha256": "d1b5804b7dfe8e45397cc05da0f4fa7601eefe36c1775cc1b9d3ae45887c0a4c"
        },
        "downloads": -1,
        "filename": "EXCAT_Sync-0.0.24-py3-none-any.whl",
        "has_sig": false,
        "md5_digest": "287a089f6c3d9fbc151a2a74ea496ffa",
        "packagetype": "bdist_wheel",
        "python_version": "py3",
        "requires_python": ">=3.6",
        "size": 126132,
        "upload_time": "2021-03-10T10:22:36",
        "upload_time_iso_8601": "2021-03-10T10:22:36.963225Z",
        "url": "https://files.pythonhosted.org/packages/8c/fa/be6eb5cc18d60049e0f552f6e72dc06b9e366970f8c5efd7b02ed96b6a33/EXCAT_Sync-0.0.24-py3-none-any.whl",
        "yanked": false,
        "yanked_reason": null
      },
      {
        "comment_text": "",
        "digests": {
          "blake2b_256": "64eae6d72b8dc11fd47bf5638e187954a67ac89b92109e260cee643e1dfff351",
          "md5": "2be369098c68102d1c8ba395fa8ddf8f",
          "sha256": "51d27871cb4c691882df13912624362a5ebf915a3943d2a78d67f0e665d89856"
        },
        "downloads": -1,
        "filename": "EXCAT-Sync-0.0.24.tar.gz",
        "has_sig": false,
        "md5_digest": "2be369098c68102d1c8ba395fa8ddf8f",
        "packagetype": "sdist",
        "python_version": "source",
        "requires_python": ">=3.6",
        "size": 60718,
        "upload_time": "2021-03-10T10:23:07",
        "upload_time_iso_8601": "2021-03-10T10:23:07.920776Z",
        "url": "https://files.pythonhosted.org/packages/64/ea/e6d72b8dc11fd47bf5638e187954a67ac89b92109e260cee643e1dfff351/EXCAT-Sync-0.0.24.tar.gz",
        "yanked": false,
        "yanked_reason": null
      }
    ],
    "0.0.25": [
      {
        "comment_text": "",
        "digests": {
          "blake2b_256": "087d05c66a270a64ed021e841319438beab29bfc05aecdcc0ed2d7e6df7b4a53",
          "md5": "e078262df0c118a1b05a9ea6e61df1f6",
          "sha256": "b1f1c8c1f3d7958217f88822fd8ccb4d386541cfa8e71939e0dcb7df7b7c1bbe"
        },
        "downloads": -1,
        "filename": "EXCAT_Sync-0.0.25-py3-none-any.whl",
        "has_sig": false,
        "md5_digest": "e078262df0c118a1b05a9ea6e61df1f6",
        "packagetype": "bdist_wheel",
        "python_version": "py3",
        "requires_python": ">=3.6",
        "size": 126198,
        "upload_time": "2021-03-12T15:45:52",
        "upload_time_iso_8601": "2021-03-12T15:45:52.122292Z",
        "url": "https://files.pythonhosted.org/packages/08/7d/05c66a270a64ed021e841319438beab29bfc05aecdcc0ed2d7e6df7b4a53/EXCAT_Sync-0.0.25-py3-none-any.whl",
        "yanked": false,
        "yanked_reason": null
      },
      {
        "comment_text": "",
        "digests": {
          "blake2b_256": "ec27288c0e4243e4df761e2cccd319f24659560ee61ba1a6d65c54e8a2da0977",
          "md5": "de35ee4b5a9c62ad67c139c83287ed95",
          "sha256": "5c4f6e7c17d4f1e475edbe1c0ccae2cb77b9f3f2d2c2cd72bc0e2f68bb58fa0b"
        },
        "downloads": -1,
        "filename": "EXCAT-Sync-0.0.25.tar.gz",
        "has_sig": false,
        "md5_digest": "de35ee4b5a9c62ad67c139c83287ed95",
        "packagetype": "sdist",
        "python_version": "source",
        "requires_python": ">=3.6",
        "size": 60776,
        "upload_time": "2021-03-12T15:46:16",
        "upload_time_iso_8601": "2021-03-12T15:46:16.475992Z",
        "url": "https://files.pythonhosted.org/packages/ec/27/288c0e4243e4df761e2cccd319f24659560ee61ba1a6d65c54e8a2da0977/EXCAT-Sync-0.0.25.tar.gz",
        "yanked": false,
        "yanked_reason": null
      }
    ],
    "0.0.27": [
      {
        "comment_text": "",
        "digests": {
          "blake2b_256": "ccc7b2f37d10a6b3f2268bb142691cbb21ffe2aa3b028f089c9a19b2c91e7680",
          "md5": "0d91a11ff1347d4d6d33832c08ee50ba",
          "sha256": "13096bc7d515b594626853f034c0b8521c4b04d61efaa256c13dc4e2346c169f"
        },
        "downloads": -1,
        "filename": "EXCAT_Sync-0.0.27-py3-none-any.whl",
        "has_sig": false,
        "md5_digest": "0d91a11ff1347d4d6d33832c08ee50ba",
        "packagetype": "bdist_wheel",
        "python_version": "py3",
        "requires_python": ">=3.6",
        "size": 126684,
        "upload_time": "2021-04-08T16:15:13",
        "upload_time_iso_8601": "2021-04-08T16:15:13.554242Z",
        "url": "https://files.pythonhosted.org/packages/cc/c7/b2f37d10a6b3f2268bb142691cbb21ffe2aa3b028f089c9a19b2c91e7680/EXCAT_Sync-0.0.27-py3-none-any.whl",
        "yanked": false,
        "yanked_reason": null
      },
      {
        "comment_text": "",
        "digests": {
          "blake2b_256": "14bbcc39162b72e645b48257448affd7f556378362a265da67ef65cae7115202",
          "md5": "12d233fabfb5849e91f7936bee4af9af",
          "sha256": "29e69dcb5087506c269bb36a8b0121bb379cb4be51603165d2fac1a10f2d6b63"
        },
        "downloads": -1,
        "filename": "EXCAT-Sync-0.0.27.tar.gz",
        "has_sig": false,
        "md5_digest": "12d233fabfb5849e91f7936bee4af9af",
        "packagetype": "sdist",
        "python_version": "source",
        "requires_python": ">=3.6",
        "size": 61268,
        "upload_time": "2021-04-08T16:15:27",
        "upload_time_iso_8601": "2021-04-08T16:15:27.664714Z",
        "url": "https://files.pythonhosted.org/packages/14/bb/cc39162b72e645b48257448affd7f556378362a265da67ef65cae7115202/EXCAT-Sync-0.0.27.tar.gz",
        "yanked": false,
        "yanked_reason": null
      }
    ],
    "0.0.28": [
      {
        "comment_text": "",
        "digests": {
          "blake2b_256": "8062fb4387be7169cfe324baf1b8db97488495c32940a103f37b0c511b2de81c",
          "md5": "3bc1da992ba320ca930b0c17eef43759",
          "sha256": "ea6aa3707f06434db80e8e3c50258445e3584f8319164a9bbe4a05e2c3eb877b"
        },
        "downloads": -1,
        "filename": "EXCAT_Sync-0.0.28-py3-none-any.whl",
        "has_sig": false,
        "md5_digest": "3bc1da992ba320ca930b0c17eef43759",
        "packagetype": "bdist_wheel",
        "python_version": "py3",
        "requires_python": ">=3.6",
        "size": 126763,
        "upload_time": "2021-04-13T11:45:13",
        "upload_time_iso_8601": "2021-04-13T11:45:13.536759Z",
        "url": "https://files.pythonhosted.org/packages/80/62/fb4387be7169cfe324baf1b8db97488495c32940a103f37b0c511b2de81c/EXCAT_Sync-0.0.28-py3-none-any.whl",
        "yanked": false,
        "yanked_reason": null
      },
      {
        "comment_text": "",
        "digests": {
          "blake2b_256": "1c5753dfed02873a88386d563dedff7632816c112a4ec573fe7eddc24135709f",
          "md5": "09096a9482409d3b564d6873d7103432",
          "sha256": "ed32e0294caba38ea8a0d5aec28f57f35553190d03c3358395e043a53a84f26a"
        },
        "downloads": -1,
        "filename": "EXCAT-Sync-0.0.28.tar.gz",
        "has_sig": false,
        "md5_digest": "09096a9482409d3b564d6873d7103432",
        "packagetype": "sdist",
        "python_version": "source",
        "requires_python": ">=3.6",
        "size": 62072,
        "upload_time": "2021-04-13T11:45:27",
        "upload_time_iso_8601": "2021-04-13T11:45:27.842788Z",
        "url": "https://files.pythonhosted.org/packages/1c/57/53dfed02873a88386d563dedff7632816c112a4ec573fe7eddc24135709f/EXCAT-Sync-0.0.28.tar.gz",
        "yanked": false,
        "yanked_reason": null
      }
    ],
    "0.0.29": [
      {
        "comment_text": "",
        "digests": {
          "blake2b_256": "0f18c2f6cc53dffe59aa9de8c3a8b0338f549f427fb03bd21466a3c76a13ae9f",
          "md5": "3c43dd4849b09b311618220deab58432",
          "sha256": "df0bae2ef04eef5f129a386f5cff2b5415627c9214bd426182685a7d28250618"
        },
        "downloads": -1,
        "filename": "EXCAT_Sync-0.0.29-py3-none-any.whl",
        "has_sig": false,
        "md5_digest": "3c43dd4849b09b311618220deab58432",
        "packagetype": "bdist_wheel",
        "python_version": "py3",
        "requires_python": ">=3.6",
        "size": 126780,
        "upload_time": "2021-09-15T07:05:20",
        "upload_time_iso_8601": "2021-09-15T07:05:20.456691Z",
        "url": "https://files.pythonhosted.org/packages/0f/18/c2f6cc53dffe59aa9de8c3a8b0338f549f427fb03bd21466a3c76a13ae9f/EXCAT_Sync-0.0.29-py3-none-any.whl",
        "yanked": false,
        "yanked_reason": null
      },
      {
        "comment_text": "",
        "digests": {
          "blake2b_256": "d01095ef51179d9390933680ca63509e05edd27ba93c26693eb72b943e08be45",
          "md5": "73a5a6511f430dfcf3c67b6508da2ecf",
          "sha256": "16afe91481ad3281ba043fbcdc274628523875b50ad3e19798d10a4be5aa6310"
        },
        "downloads": -1,
        "filename": "EXCAT-Sync-0.0.29.tar.gz",
        "has_sig": false,
        "md5_digest": "73a5a6511f430dfcf3c67b6508da2ecf",
        "packagetype": "sdist",
        "python_version": "source",
        "requires_python": ">=3.6",
        "size": 61945,
        "upload_time": "2021-09-15T07:05:22",
        "upload_time_iso_8601": "2021-09-15T07:05:22.106789Z",
        "url": "https://files.pythonhosted.org/packages/d0/10/95ef51179d9390933680ca63509e05edd27ba93c26693eb72b943e08be45/EXCAT-Sync-0.0.29.tar.gz",
        "yanked": false,
        "yanked_reason": null
      }
    ],
    "0.0.3": [
      {
        "comment_text": "",
        "digests": {
          "blake2b_256": "7233e1bf44b936235a3f2841ebd5af3cd9ef5dad7b36fa012506ec487bac645c",
          "md5": "bd5ca2c0395d2365156d44c6d191c47a",
          "sha256": "b195bdbaf0c9902a9ceec93fb16c57277a612f6a6c112f9a932af21f10bbeec8"
        },
        "downloads": -1,
        "filename": "EXCAT_Sync-0.0.3-py3-none-any.whl",
        "has_sig": false,
        "md5_digest": "bd5ca2c0395d2365156d44c6d191c47a",
        "packagetype": "bdist_wheel",
        "python_version": "py3",
        "requires_python": ">=3.6",
        "size": 5268,
        "upload_time": "2020-03-10T08:11:17",
        "upload_time_iso_8601": "2020-03-10T08:11:17.013000Z",
        "url": "https://files.pythonhosted.org/packages/72/33/e1bf44b936235a3f2841ebd5af3cd9ef5dad7b36fa012506ec487bac645c/EXCAT_Sync-0.0.3-py3-none-any.whl",
        "yanked": false,
        "yanked_reason": null
      },
      {
        "comment_text": "",
        "digests": {
          "blake2b_256": "f58ffd7ed62f91c191cd2337f66eb5f4dfb6658de7e985a493ac405571f04eb5",
          "md5": "dac9f5e1b7e2f2f9448ffda7f400ee49",
          "sha256": "1e938d2ee7fdc7d061d7d867b0f1df30ec3d7c23d0a6d4d349354cf70c2869f2"
        },
        "downloads": -1,
        "filename": "EXCAT-Sync-0.0.3.tar.gz",
        "has_sig": false,
        "md5_digest": "dac9f5e1b7e2f2f9448ffda7f400ee49",
        "packagetype": "sdist",
        "python_version": "source",
        "requires_python": ">=3.6",
        "size": 3595,
        "upload_time": "2020-03-10T08:11:19",
        "upload_time_iso_8601": "2020-03-10T08:11:19.689040Z",
        "url": "https://files.pythonhosted.org/packages/f5/8f/fd7ed62f91c191cd2337f66eb5f4dfb6658de7e985a493ac405571f04eb5/EXCAT-Sync-0.0.3.tar.gz",
        "yanked": false,
        "yanked_reason": null
      }
    ],
    "0.0.30": [
      {
        "comment_text": "",
        "digests": {
          "blake2b_256": "f19daaf3047a3166d829e19d0fd0a276236eb8cbd166611d2a7f1f8fae561fd6",
          "md5": "1b54cf710858c4e2b0d4c942d3eaacf6",
          "sha256": "07a314d6c2e6b1f939494422b5ff0da05f500cf92b1842301b353d9673700482"
        },
        "downloads": -1,
        "filename": "EXCAT_Sync-0.0.30-py3-none-any.whl",
        "has_sig": false,
        "md5_digest": "1b54cf710858c4e2b0d4c942d3eaacf6",
        "packagetype": "bdist_wheel",
        "python_version": "py3",
        "requires_python": ">=3.6",
        "size": 126794,
        "upload_time": "2021-12-03T09:07:05",
        "upload_time_iso_8601": "2021-12-03T09:07:05.273302Z",
        "url": "https://files.pythonhosted.org/packages/f1/9d/aaf3047a3166d829e19d0fd0a276236eb8cbd166611d2a7f1f8fae561fd6/EXCAT_Sync-0.0.30-py3-none-any.whl",
        "yanked": false,
        "yanked_reason": null
      },
      {
        "comment_text": "",
        "digests": {
          "blake2b_256": "616cfb78dd2677730bd193a6e7e2d580be12eb48802f84c3f63266008d218986",
          "md5": "62d142a6b69787ef415a36078d987a30",
          "sha256": "de671ae79e007dc4bccb9763c9282affbd654c5d2820d52997b5183cccfe8fec"
        },
        "downloads": -1,
        "filename": "EXCAT-Sync-0.0.30.tar.gz",
        "has_sig": false,
        "md5_digest": "62d142a6b69787ef415a36078d987a30",
        "packagetype": "sdist",
        "python_version": "source",
        "requires_python": ">=3.6",
        "size": 61950,
        "upload_time": "2021-12-03T09:07:08",
        "upload_time_iso_8601": "2021-12-03T09:07:08.126803Z",
        "url": "https://files.pythonhosted.org/packages/61/6c/fb78dd2677730bd193a6e7e2d580be12eb48802f84c3f63266008d218986/EXCAT-Sync-0.0.30.tar.gz",
        "yanked": false,
        "yanked_reason": null
      }
    ],
    "0.0.32": [
      {
        "comment_text": "",
        "digests": {
          "blake2b_256": "9a11b3fe07f3953452c6ad70b80e7c738ef4c711a71a5504785386178353f311",
          "md5": "16cb5ad31a86eb13892292a134f920d8",
          "sha256": "b12b2c95a0186f702661094a6c5bf52144703eb827178d95e63968127118c64c"
        },
        "downloads": -1,
        "filename": "EXCAT_Sync-0.0.32-py3-none-any.whl",
        "has_sig": false,
        "md5_digest": "16cb5ad31a86eb13892292a134f920d8",
        "packagetype": "bdist_wheel",
        "python_version": "py3",
        "requires_python": ">=3.6",
        "size": 126788,
        "upload_time": "2022-01-18T14:28:57",
        "upload_time_iso_8601": "2022-01-18T14:28:57.365641Z",
        "url": "https://files.pythonhosted.org/packages/9a/11/b3fe07f3953452c6ad70b80e7c738ef4c711a71a5504785386178353f311/EXCAT_Sync-0.0.32-py3-none-any.whl",
        "yanked": false,
        "yanked_reason": null
      },
      {
        "comment_text": "",
        "digests": {
          "blake2b_256": "95de4db1521f89b5aacfb6d965d3e0a142977c616899074b4021b80ada9ad292",
          "md5": "fbaea21da2f6b71528a7eb3a0466d01b",
          "sha256": "4738e79448fb9637ac20807ab8c5337b3e64796bb61a64f858219ee25f556079"
        },
        "downloads": -1,
        "filename": "EXCAT-Sync-0.0.32.tar.gz",
        "has_sig": false,
        "md5_digest": "fbaea21da2f6b71528a7eb3a0466d01b",
        "packagetype": "sdist",
        "python_version": "source",
        "requires_python": ">=3.6",
        "size": 61940,
        "upload_time": "2022-01-18T14:29:00",
        "upload_time_iso_8601": "2022-01-18T14:29:00.633591Z",
        "url": "https://files.pythonhosted.org/packages/95/de/4db1521f89b5aacfb6d965d3e0a142977c616899074b4021b80ada9ad292/EXCAT-Sync-0.0.32.tar.gz",
        "yanked": false,
        "yanked_reason": null
      }
    ],
    "0.0.33": [
      {
        "comment_text": "",
        "digests": {
          "blake2b_256": "b22daccf65f10bf994e07636d55ab1a074481dfe65980698e65396148851e1d4",
          "md5": "9b237248675d83e2fabbc7299ae0d0e2",
          "sha256": "3898a97ae7cd7dd1e155b17f1bc18fccea197b22d4423b15f28978616c2498da"
        },
        "downloads": -1,
        "filename": "EXCAT_Sync-0.0.33-py3-none-any.whl",
        "has_sig": false,
        "md5_digest": "9b237248675d83e2fabbc7299ae0d0e2",
        "packagetype": "bdist_wheel",
        "python_version": "py3",
        "requires_python": ">=3.6",
        "size": 127094,
        "upload_time": "2022-06-08T20:24:54",
        "upload_time_iso_8601": "2022-06-08T20:24:54.691521Z",
        "url": "https://files.pythonhosted.org/packages/b2/2d/accf65f10bf994e07636d55ab1a074481dfe65980698e65396148851e1d4/EXCAT_Sync-0.0.33-py3-none-any.whl",
        "yanked": false,
        "yanked_reason": null
      },
      {
        "comment_text": "",
        "digests": {
          "blake2b_256": "77f73e70dc1e4970aa67ee2addf9402100d3459b200d7ac33361a309cc0ba3d6",
          "md5": "37a37b4e17f0362051c34da06e436906",
          "sha256": "4d3c9490643c4b66eece3337428d1e519c7fe02b1bdef9fb6b4b401d1811aa38"
        },
        "downloads": -1,
        "filename": "EXCAT-Sync-0.0.33.tar.gz",
        "has_sig": false,
        "md5_digest": "37a37b4e17f0362051c34da06e436906",
        "packagetype": "sdist",
        "python_version": "source",
        "requires_python": ">=3.6",
        "size": 65788,
        "upload_time": "2022-06-08T20:25:01",
        "upload_time_iso_8601": "2022-06-08T20:25:01.368885Z",
        "url": "https://files.pythonhosted.org/packages/77/f7/3e70dc1e4970aa67ee2addf9402100d3459b200d7ac33361a309cc0ba3d6/EXCAT-Sync-0.0.33.tar.gz",
        "yanked": false,
        "yanked_reason": null
      }
    ],
    "0.0.34": [
      {
        "comment_text": "",
        "digests": {
          "blake2b_256": "b49e03b6bc29eaef5617021ecd7c4eebc49c9b8e8e019a364977ee74dd490ed9",
          "md5": "a02f17f40beea9bdf9031bbfd14c51ec",
          "sha256": "72f67eae32904f0f844f910ce2a1c40c6bbee99c3763441568da394823a8c149"
        },
        "downloads": -1,
        "filename": "EXCAT_Sync-0.0.34-py3-none-any.whl",
        "has_sig": false,
        "md5_digest": "a02f17f40beea9bdf9031bbfd14c51ec",
        "packagetype": "bdist_wheel",
        "python_version": "py3",
        "requires_python": ">=3.6",
        "size": 127352,
        "upload_time": "2022-06-09T12:12:47",
        "upload_time_iso_8601": "2022-06-09T12:12:47.165646Z",
        "url": "https://files.pythonhosted.org/packages/b4/9e/03b6bc29eaef5617021ecd7c4eebc49c9b8e8e019a364977ee74dd490ed9/EXCAT_Sync-0.0.34-py3-none-any.whl",
        "yanked": false,
        "yanked_reason": null
      },
      {
        "comment_text": "",
        "digests": {
          "blake2b_256": "013b2b428561ef7f280a5c157b56e670bd32dd00326e402d82d834f5757d288c",
          "md5": "968212b040e3df47d6d8cae94896026e",
          "sha256": "ff3409344b732cad8e2212ea9f7f3bd9108b0c3ff66cfd41c7e582a2c7df812d"
        },
        "downloads": -1,
        "filename": "EXCAT-Sync-0.0.34.tar.gz",
        "has_sig": false,
        "md5_digest": "968212b040e3df47d6d8cae94896026e",
        "packagetype": "sdist",
        "python_version": "source",
        "requires_python": ">=3.6",
        "size": 66032,
        "upload_time": "2022-06-09T12:12:53",
        "upload_time_iso_8601": "2022-06-09T12:12:53.739190Z",
        "url": "https://files.pythonhosted.org/packages/01/3b/2b428561ef7f280a5c157b56e670bd32dd00326e402d82d834f5757d288c/EXCAT-Sync-0.0.34.tar.gz",
        "yanked": false,
        "yanked_reason": null
      }
    ],
    "0.0.35": [
      {
        "comment_text": "",
        "digests": {
          "blake2b_256": "1da99e364462286712dbdc38abbef4808fbfc658ae2231c52d886e321788f949",
          "md5": "95c99871923a85ce22f0799127eca5ca",
          "sha256": "5fb44a7ce1ae6834fcba6538fe12b9eb6dabb97ffef5e2528902cd8efb4efd6e"
        },
        "downloads": -1,
        "filename": "EXCAT_Sync-0.0.35-py3-none-any.whl",
        "has_sig": false,
        "md5_digest": "95c99871923a85ce22f0799127eca5ca",
        "packagetype": "bdist_wheel",
        "python_version": "py3",
        "requires_python": ">=3.6",
        "size": 153820,
        "upload_time": "2023-01-04T12:26:27",
        "upload_time_iso_8601": "2023-01-04T12:26:27.024303Z",
        "url": "https://files.pythonhosted.org/packages/1d/a9/9e364462286712dbdc38abbef4808fbfc658ae2231c52d886e321788f949/EXCAT_Sync-0.0.35-py3-none-any.whl",
        "yanked": false,
        "yanked_reason": null
      },
      {
        "comment_text": "",
        "digests": {
          "blake2b_256": "a0ee84ccab15f21326fbe379a0bb1d052798e08ecb179b259dfac10b375860f5",
          "md5": "f5207c2d49db7aceda973a0328d4387e",
          "sha256": "ac578dcdcb4e41f9d4ffd3af3a9d8f03a0648101a4a60c70cbc1c8deed4b68f3"
        },
        "downloads": -1,
        "filename": "EXCAT-Sync-0.0.35.tar.gz",
        "has_sig": false,
        "md5_digest": "f5207c2d49db7aceda973a0328d4387e",
        "packagetype": "sdist",
        "python_version": "source",
        "requires_python": ">=3.6",
        "size": 78427,
        "upload_time": "2023-01-04T12:26:29",
        "upload_time_iso_8601": "2023-01-04T12:26:29.095549Z",
        "url": "https://files.pythonhosted.org/packages/a0/ee/84ccab15f21326fbe379a0bb1d052798e08ecb179b259dfac10b375860f5/EXCAT-Sync-0.0.35.tar.gz",
        "yanked": false,
        "yanked_reason": null
      }
    ],
    "0.0.36": [
      {
        "comment_text": "",
        "digests": {
          "blake2b_256": "e7cc80a16b7cfce014e3e46b38c3505826d7acf61f1adccc8333c5a83e7698c5",
          "md5": "595a97ca911c194eb147ec1d959e73aa",
          "sha256": "77ae2934b53c0c5e93ad121896ad3dd7fe5008e4fdc6bb51978805f264baa67b"
        },
        "downloads": -1,
        "filename": "EXCAT_Sync-0.0.36-py3-none-any.whl",
        "has_sig": false,
        "md5_digest": "595a97ca911c194eb147ec1d959e73aa",
        "packagetype": "bdist_wheel",
        "python_version": "py3",
        "requires_python": ">=3.6",
        "size": 154296,
        "upload_time": "2023-01-05T16:32:26",
        "upload_time_iso_8601": "2023-01-05T16:32:26.353479Z",
        "url": "https://files.pythonhosted.org/packages/e7/cc/80a16b7cfce014e3e46b38c3505826d7acf61f1adccc8333c5a83e7698c5/EXCAT_Sync-0.0.36-py3-none-any.whl",
        "yanked": false,
        "yanked_reason": null
      },
      {
        "comment_text": "",
        "digests": {
          "blake2b_256": "1b72efe8422fdceeb6f9a996b710e78b6ffdef32aef614d004187b8244ec4795",
          "md5": "b613e69f4d15235089e57cdbf51379b3",
          "sha256": "917aad71581f505c84c022d1d84081d2476be5b56312966203ce7b54645f0f19"
        },
        "downloads": -1,
        "filename": "EXCAT-Sync-0.0.36.tar.gz",
        "has_sig": false,
        "md5_digest": "b613e69f4d15235089e57cdbf51379b3",
        "packagetype": "sdist",
        "python_version": "source",
        "requires_python": ">=3.6",
        "size": 79573,
        "upload_time": "2023-01-05T16:32:30",
        "upload_time_iso_8601": "2023-01-05T16:32:30.730705Z",
        "url": "https://files.pythonhosted.org/packages/1b/72/efe8422fdceeb6f9a996b710e78b6ffdef32aef614d004187b8244ec4795/EXCAT-Sync-0.0.36.tar.gz",
        "yanked": false,
        "yanked_reason": null
      }
    ],
    "0.0.37": [
      {
        "comment_text": "",
        "digests": {
          "blake2b_256": "2713d6f61cc504cf365941ffab3df2910e7b215213d5569416b92bd1181311a3",
          "md5": "a93c55247c8243ab90b7abf89f48cbbe",
          "sha256": "2d9637fbde184e7609b563c7077be9dad6ac4e6e3ff43c2cac8ae36c3da03b5f"
        },
        "downloads": -1,
        "filename": "EXCAT_Sync-0.0.37-py3-none-any.whl",
        "has_sig": false,
        "md5_digest": "a93c55247c8243ab90b7abf89f48cbbe",
        "packagetype": "bdist_wheel",
        "python_version": "py3",
        "requires_python": ">=3.6",
        "size": 154299,
        "upload_time": "2023-01-23T13:40:53",
        "upload_time_iso_8601": "2023-01-23T13:40:53.803955Z",
        "url": "https://files.pythonhosted.org/packages/27/13/d6f61cc504cf365941ffab3df2910e7b215213d5569416b92bd1181311a3/EXCAT_Sync-0.0.37-py3-none-any.whl",
        "yanked": false,
        "yanked_reason": null
      },
      {
        "comment_text": "",
        "digests": {
          "blake2b_256": "b633721931d7fb105f71e94a901b8bd8492ff34d026044600ae970b7f24da7b8",
          "md5": "341cf7dd6fde0a5a89baba3580964dc9",
          "sha256": "7b92b4e2f2b133012ef4c719d192dd78479332fa941ffe4a06cc50f5cec8a48e"
        },
        "downloads": -1,
        "filename": "EXCAT-Sync-0.0.37.tar.gz",
        "has_sig": false,
        "md5_digest": "341cf7dd6fde0a5a89baba3580964dc9",
        "packagetype": "sdist",
        "python_version": "source",
        "requires_python": ">=3.6",
        "size": 78971,
        "upload_time": "2023-01-23T13:40:58",
        "upload_time_iso_8601": "2023-01-23T13:40:58.094666Z",
        "url": "https://files.pythonhosted.org/packages/b6/33/721931d7fb105f71e94a901b8bd8492ff34d026044600ae970b7f24da7b8/EXCAT-Sync-0.0.37.tar.gz",
        "yanked": false,
        "yanked_reason": null
      }
    ],
    "0.0.38": [
      {
        "comment_text": "",
        "digests": {
          "blake2b_256": "3ede7bd0c44a8c61455558740e775a0aeead875af28c8b9e524de7ad85315275",
          "md5": "f1a8dd7e09c47650358ffe2e67588c0d",
          "sha256": "d3e7d9ff6db0f2f20ce11d3aca884b52a734e5b6953c942ca0d1752b73a19731"
        },
        "downloads": -1,
        "filename": "EXCAT_Sync-0.0.38-py3-none-any.whl",
        "has_sig": false,
        "md5_digest": "f1a8dd7e09c47650358ffe2e67588c0d",
        "packagetype": "bdist_wheel",
        "python_version": "py3",
        "requires_python": ">=3.6",
        "size": 154675,
        "upload_time": "2023-03-27T06:19:49",
        "upload_time_iso_8601": "2023-03-27T06:19:49.161989Z",
        "url": "https://files.pythonhosted.org/packages/3e/de/7bd0c44a8c61455558740e775a0aeead875af28c8b9e524de7ad85315275/EXCAT_Sync-0.0.38-py3-none-any.whl",
        "yanked": false,
        "yanked_reason": null
      },
      {
        "comment_text": "",
        "digests": {
          "blake2b_256": "a8991d5dbcaca4f30d411ace78a5add6fe676344e48674e73d806fd53caad46a",
          "md5": "5e313638da1498f3cecc570c4e873436",
          "sha256": "7a166add6c53f89ed369763f1955ad352a49ac0c54d4e1af1cd35dc0148f54dc"
        },
        "downloads": -1,
        "filename": "EXCAT-Sync-0.0.38.tar.gz",
        "has_sig": false,
        "md5_digest": "5e313638da1498f3cecc570c4e873436",
        "packagetype": "sdist",
        "python_version": "source",
        "requires_python": ">=3.6",
        "size": 79228,
        "upload_time": "2023-03-27T06:19:53",
        "upload_time_iso_8601": "2023-03-27T06:19:53.878084Z",
        "url": "https://files.pythonhosted.org/packages/a8/99/1d5dbcaca4f30d411ace78a5add6fe676344e48674e73d806fd53caad46a/EXCAT-Sync-0.0.38.tar.gz",
        "yanked": false,
        "yanked_reason": null
      }
    ],
    "0.0.4": [
      {
        "comment_text": "",
        "digests": {
          "blake2b_256": "0db534b21e6fadfff6b6ef9bd893137ac26e8595406a56078634dc748619f73c",
          "md5": "1e3640f059eff7e8fae7f10dfa9499a3",
          "sha256": "8202c9bd4923df712a0ce5d629b5539031fdb25dbf99ec05d589709ce0ea6956"
        },
        "downloads": -1,
        "filename": "EXCAT_Sync-0.0.4-py3-none-any.whl",
        "has_sig": false,
        "md5_digest": "1e3640f059eff7e8fae7f10dfa9499a3",
        "packagetype": "bdist_wheel",
        "python_version": "py3",
        "requires_python": ">=3.6",
        "size": 5305,
        "upload_time": "2020-03-10T20:17:23",
        "upload_time_iso_8601": "2020-03-10T20:17:23.529066Z",
        "url": "https://files.pythonhosted.org/packages/0d/b5/34b21e6fadfff6b6ef9bd893137ac26e8595406a56078634dc748619f73c/EXCAT_Sync-0.0.4-py3-none-any.whl",
        "yanked": false,
        "yanked_reason": null
      },
      {
        "comment_text": "",
        "digests": {
          "blake2b_256": "afa7b4211cb51844912e69852454df21e824732bd1313c5dc064e6328440c480",
          "md5": "857e5661d9816a0d5a404383f9271172",
          "sha256": "11aea6e4ec108aa973a9163fe37d7fc243a9b48f4c25185d28b70edba963058e"
        },
        "downloads": -1,
        "filename": "EXCAT-Sync-0.0.4.tar.gz",
        "has_sig": false,
        "md5_digest": "857e5661d9816a0d5a404383f9271172",
        "packagetype": "sdist",
        "python_version": "source",
        "requires_python": ">=3.6",
        "size": 3630,
        "upload_time": "2020-03-10T20:17:27",
        "upload_time_iso_8601": "2020-03-10T20:17:27.752970Z",
        "url": "https://files.pythonhosted.org/packages/af/a7/b4211cb51844912e69852454df21e824732bd1313c5dc064e6328440c480/EXCAT-Sync-0.0.4.tar.gz",
        "yanked": false,
        "yanked_reason": null
      }
    ],
    "0.0.5": [
      {
        "comment_text": "",
        "digests": {
          "blake2b_256": "863e1c4fef36fd215a2164e1609654bc1bbe96fbd9c6ea1b8dba2fc928c3077b",
          "md5": "65b0cbfadd9fb3a9cfc3157bdab6f8d1",
          "sha256": "c8429dde29963166a0c8876133818c12dee4ee36831c8a00b8703d0cb82b690e"
        },
        "downloads": -1,
        "filename": "EXCAT_Sync-0.0.5-py3-none-any.whl",
        "has_sig": false,
        "md5_digest": "65b0cbfadd9fb3a9cfc3157bdab6f8d1",
        "packagetype": "bdist_wheel",
        "python_version": "py3",
        "requires_python": ">=3.6",
        "size": 6517,
        "upload_time": "2020-03-12T08:48:17",
        "upload_time_iso_8601": "2020-03-12T08:48:17.650234Z",
        "url": "https://files.pythonhosted.org/packages/86/3e/1c4fef36fd215a2164e1609654bc1bbe96fbd9c6ea1b8dba2fc928c3077b/EXCAT_Sync-0.0.5-py3-none-any.whl",
        "yanked": false,
        "yanked_reason": null
      },
      {
        "comment_text": "",
        "digests": {
          "blake2b_256": "9ab7cfdaaa0bd42ca7fd0781cf435d510e93adbbf7c210919da2a3ba887e847e",
          "md5": "e0c3a55ed5131ca09dc862dc0c4aea2c",
          "sha256": "9aaee07bca5d9e7bde244d54c8deb235188d5934ce57b52fafb4636b3b3c497f"
        },
        "downloads": -1,
        "filename": "EXCAT-Sync-0.0.5.tar.gz",
        "has_sig": false,
        "md5_digest": "e0c3a55ed5131ca09dc862dc0c4aea2c",
        "packagetype": "sdist",
        "python_version": "source",
        "requires_python": ">=3.6",
        "size": 4853,
        "upload_time": "2020-03-12T08:48:19",
        "upload_time_iso_8601": "2020-03-12T08:48:19.034015Z",
        "url": "https://files.pythonhosted.org/packages/9a/b7/cfdaaa0bd42ca7fd0781cf435d510e93adbbf7c210919da2a3ba887e847e/EXCAT-Sync-0.0.5.tar.gz",
        "yanked": false,
        "yanked_reason": null
      }
    ],
    "0.0.6": [
      {
        "comment_text": "",
        "digests": {
          "blake2b_256": "e7570d3207ed1c490082eee669a9a3aafb43537e6eddb088c245bb20ca5563b4",
          "md5": "dfa8a987cd1c28033f44c808b35fb597",
          "sha256": "24f82ce6c6ff9ff3213c5fcd24ed2f283c8eee8a819083fb3e9fe65a77f84a29"
        },
        "downloads": -1,
        "filename": "EXCAT_Sync-0.0.6-py3-none-any.whl",
        "has_sig": false,
        "md5_digest": "dfa8a987cd1c28033f44c808b35fb597",
        "packagetype": "bdist_wheel",
        "python_version": "py3",
        "requires_python": ">=3.6",
        "size": 6701,
        "upload_time": "2020-03-16T12:22:14",
        "upload_time_iso_8601": "2020-03-16T12:22:14.219256Z",
        "url": "https://files.pythonhosted.org/packages/e7/57/0d3207ed1c490082eee669a9a3aafb43537e6eddb088c245bb20ca5563b4/EXCAT_Sync-0.0.6-py3-none-any.whl",
        "yanked": false,
        "yanked_reason": null
      },
      {
        "comment_text": "",
        "digests": {
          "blake2b_256": "fb5949b7f325ad14c9239e9660a093cce3d7a1fa6204efbffa7df0ef5dc555f8",
          "md5": "82117ae38abd00178b240ffd9dd92a4b",
          "sha256": "448d4790e3e904ad1f88c16792b1b28132abb6df5e9e1909d62edcc18c25205a"
        },
        "downloads": -1,
        "filename": "EXCAT-Sync-0.0.6.tar.gz",
        "has_sig": false,
        "md5_digest": "82117ae38abd00178b240ffd9dd92a4b",
        "packagetype": "sdist",
        "python_version": "source",
        "requires_python": ">=3.6",
        "size": 5037,
        "upload_time": "2020-03-16T12:22:15",
        "upload_time_iso_8601": "2020-03-16T12:22:15.708202Z",
        "url": "https://files.pythonhosted.org/packages/fb/59/49b7f325ad14c9239e9660a093cce3d7a1fa6204efbffa7df0ef5dc555f8/EXCAT-Sync-0.0.6.tar.gz",
        "yanked": false,
        "yanked_reason": null
      }
    ],
    "0.0.7": [
      {
        "comment_text": "",
        "digests": {
          "blake2b_256": "51a33611c4ec398723e584d7b29a86f914dbf03de3142e0a0c11eeed7d1ef113",
          "md5": "a9491d2ac674b192ae783af7af870e48",
          "sha256": "78aa11b7ef53d05a73dea608ac79ac976284e2ed04224459f2460a2e46663658"
        },
        "downloads": -1,
        "filename": "EXCAT_Sync-0.0.7-py3-none-any.whl",
        "has_sig": false,
        "md5_digest": "a9491d2ac674b192ae783af7af870e48",
        "packagetype": "bdist_wheel",
        "python_version": "py3",
        "requires_python": ">=3.6",
        "size": 6729,
        "upload_time": "2020-03-17T08:30:22",
        "upload_time_iso_8601": "2020-03-17T08:30:22.264453Z",
        "url": "https://files.pythonhosted.org/packages/51/a3/3611c4ec398723e584d7b29a86f914dbf03de3142e0a0c11eeed7d1ef113/EXCAT_Sync-0.0.7-py3-none-any.whl",
        "yanked": false,
        "yanked_reason": null
      },
      {
        "comment_text": "",
        "digests": {
          "blake2b_256": "cd47e5c3fe34557ce36797c11fcb23222dd3168d5efe92f917e3b1a41678f6e3",
          "md5": "71db5bb3b26da06dc298cebae32d3eb0",
          "sha256": "a23d2fa94ffc4c0b4c4631858cb163983221221eab9793dd8702fcf607309675"
        },
        "downloads": -1,
        "filename": "EXCAT-Sync-0.0.7.tar.gz",
        "has_sig": false,
        "md5_digest": "71db5bb3b26da06dc298cebae32d3eb0",
        "packagetype": "sdist",
        "python_version": "source",
        "requires_python": ">=3.6",
        "size": 5111,
        "upload_time": "2020-03-17T08:30:24",
        "upload_time_iso_8601": "2020-03-17T08:30:24.868300Z",
        "url": "https://files.pythonhosted.org/packages/cd/47/e5c3fe34557ce36797c11fcb23222dd3168d5efe92f917e3b1a41678f6e3/EXCAT-Sync-0.0.7.tar.gz",
        "yanked": false,
        "yanked_reason": null
      }
    ],
    "0.0.8": [
      {
        "comment_text": "",
        "digests": {
          "blake2b_256": "5c35b69773c2ed5735a891959fcdc18d21d51548f16c2f8bacc6dc75cdeaba47",
          "md5": "cebd9dbc874d0cd3c5ec8e63e07b0d83",
          "sha256": "528ce8307941e0be9bab551119e83fd6f7655542b20af8a2f2e1faa6469b63b2"
        },
        "downloads": -1,
        "filename": "EXCAT_Sync-0.0.8-py3-none-any.whl",
        "has_sig": false,
        "md5_digest": "cebd9dbc874d0cd3c5ec8e63e07b0d83",
        "packagetype": "bdist_wheel",
        "python_version": "py3",
        "requires_python": ">=3.6",
        "size": 6729,
        "upload_time": "2020-03-17T09:05:21",
        "upload_time_iso_8601": "2020-03-17T09:05:21.106781Z",
        "url": "https://files.pythonhosted.org/packages/5c/35/b69773c2ed5735a891959fcdc18d21d51548f16c2f8bacc6dc75cdeaba47/EXCAT_Sync-0.0.8-py3-none-any.whl",
        "yanked": false,
        "yanked_reason": null
      },
      {
        "comment_text": "",
        "digests": {
          "blake2b_256": "14425f8856eb45c75d096779d96ceea3bdf910bbf31788ce8f9206716b562df5",
          "md5": "fc63459051c1451a4ce65380e9449c9d",
          "sha256": "da3f640bc0978e4d6772e4aafa731880ac629f79e53c67bd26e2a7259ff4d88d"
        },
        "downloads": -1,
        "filename": "EXCAT-Sync-0.0.8.tar.gz",
        "has_sig": false,
        "md5_digest": "fc63459051c1451a4ce65380e9449c9d",
        "packagetype": "sdist",
        "python_version": "source",
        "requires_python": ">=3.6",
        "size": 5109,
        "upload_time": "2020-03-17T09:05:23",
        "upload_time_iso_8601": "2020-03-17T09:05:23.398778Z",
        "url": "https://files.pythonhosted.org/packages/14/42/5f8856eb45c75d096779d96ceea3bdf910bbf31788ce8f9206716b562df5/EXCAT-Sync-0.0.8.tar.gz",
        "yanked": false,
        "yanked_reason": null
      }
    ],
    "0.0.9": [
      {
        "comment_text": "",
        "digests": {
          "blake2b_256": "ec7aaf5d55efc4e1f67ae47557653eab384c778d1a558eef288a3c7a22ce0007",
          "md5": "446b5cbb5294e159f1178e20aa8043ff",
          "sha256": "35dd348e0daa6631806490700018850e7a434e14f256bd2da53ac669bdb85351"
        },
        "downloads": -1,
        "filename": "EXCAT_Sync-0.0.9-py3-none-any.whl",
        "has_sig": false,
        "md5_digest": "446b5cbb5294e159f1178e20aa8043ff",
        "packagetype": "bdist_wheel",
        "python_version": "py3",
        "requires_python": ">=3.6",
        "size": 7030,
        "upload_time": "2020-04-09T14:13:48",
        "upload_time_iso_8601": "2020-04-09T14:13:48.165663Z",
        "url": "https://files.pythonhosted.org/packages/ec/7a/af5d55efc4e1f67ae47557653eab384c778d1a558eef288a3c7a22ce0007/EXCAT_Sync-0.0.9-py3-none-any.whl",
        "yanked": false,
        "yanked_reason": null
      },
      {
        "comment_text": "",
        "digests": {
          "blake2b_256": "536acbfa3fb9d199133391d6d56eaaca7712a29273315e8d46098ffe1f6b8780",
          "md5": "8ed83ddff628589c075a295a499dbfc6",
          "sha256": "e075b8e15695080333a6fdabb377da05f8125467c2ef50bf321779fe9e4e7e62"
        },
        "downloads": -1,
        "filename": "EXCAT-Sync-0.0.9.tar.gz",
        "has_sig": false,
        "md5_digest": "8ed83ddff628589c075a295a499dbfc6",
        "packagetype": "sdist",
        "python_version": "source",
        "requires_python": ">=3.6",
        "size": 5386,
        "upload_time": "2020-04-09T14:13:50",
        "upload_time_iso_8601": "2020-04-09T14:13:50.994598Z",
        "url": "https://files.pythonhosted.org/packages/53/6a/cbfa3fb9d199133391d6d56eaaca7712a29273315e8d46098ffe1f6b8780/EXCAT-Sync-0.0.9.tar.gz",
        "yanked": false,
        "yanked_reason": null
      }
    ]
  },
  "urls": [
    {
      "comment_text": "",
      "digests": {
        "blake2b_256": "3ede7bd0c44a8c61455558740e775a0aeead875af28c8b9e524de7ad85315275",
        "md5": "f1a8dd7e09c47650358ffe2e67588c0d",
        "sha256": "d3e7d9ff6db0f2f20ce11d3aca884b52a734e5b6953c942ca0d1752b73a19731"
      },
      "downloads": -1,
      "filename": "EXCAT_Sync-0.0.38-py3-none-any.whl",
      "has_sig": false,
      "md5_digest": "f1a8dd7e09c47650358ffe2e67588c0d",
      "packagetype": "bdist_wheel",
      "python_version": "py3",
      "requires_python": ">=3.6",
      "size": 154675,
      "upload_time": "2023-03-27T06:19:49",
      "upload_time_iso_8601": "2023-03-27T06:19:49.161989Z",
      "url": "https://files.pythonhosted.org/packages/3e/de/7bd0c44a8c61455558740e775a0aeead875af28c8b9e524de7ad85315275/EXCAT_Sync-0.0.38-py3-none-any.whl",
      "yanked": false,
      "yanked_reason": null
    },
    {
      "comment_text": "",
      "digests": {
        "blake2b_256": "a8991d5dbcaca4f30d411ace78a5add6fe676344e48674e73d806fd53caad46a",
        "md5": "5e313638da1498f3cecc570c4e873436",
        "sha256": "7a166add6c53f89ed369763f1955ad352a49ac0c54d4e1af1cd35dc0148f54dc"
      },
      "downloads": -1,
      "filename": "EXCAT-Sync-0.0.38.tar.gz",
      "has_sig": false,
      "md5_digest": "5e313638da1498f3cecc570c4e873436",
      "packagetype": "sdist",
      "python_version": "source",
      "requires_python": ">=3.6",
      "size": 79228,
      "upload_time": "2023-03-27T06:19:53",
      "upload_time_iso_8601": "2023-03-27T06:19:53.878084Z",
      "url": "https://files.pythonhosted.org/packages/a8/99/1d5dbcaca4f30d411ace78a5add6fe676344e48674e73d806fd53caad46a/EXCAT-Sync-0.0.38.tar.gz",
      "yanked": false,
      "yanked_reason": null
    }
  ],
  "vulnerabilities": []
}