{
  "info": {
    "author": "Joey Greco",
    "author_email": "joeyagreco@gmail.com",
    "bugtrack_url": null,
    "classifiers": [],
    "description": "<div align=\"center\">\r\n    <img src=\"https://raw.githubusercontent.com/joeyagreco/leeger/main/img/leeger-logo-cropped.png\" alt=\"leeger logo\" width=\"300\"/>\r\n\r\nInstant stats for your fantasy football league.\r\n\r\n<a target=\"_blank\" href=\"https://www.python.org/downloads/\" title=\"Python version\"><img src=\"https://img.shields.io/badge/python-%3E=_3.10-teal.svg\"></a>\r\n![Main Build](https://github.com/joeyagreco/leeger/actions/workflows/main-build.yml/badge.svg)\r\n![Last Commit](https://img.shields.io/github/last-commit/joeyagreco/leeger)\r\n</div>\r\n\r\n### Table of Contents\r\n\r\n- [Overview](https://github.com/joeyagreco/leeger#overview)\r\n- [Quickstart Guide](https://github.com/joeyagreco/leeger#quickstart-guide)\r\n- [FAQ](https://github.com/joeyagreco/leeger#faq)\r\n- [Installation](https://github.com/joeyagreco/leeger#installation)\r\n- [Supported League Loaders](https://github.com/joeyagreco/leeger#supported-league-loaders)\r\n- [Stats Explained](https://github.com/joeyagreco/leeger#stats-explained)\r\n- [Running Tests](https://github.com/joeyagreco/leeger#running-tests)\r\n- [Contributing](https://github.com/joeyagreco/leeger#contributing)\r\n- [License](https://github.com/joeyagreco/leeger#license)\r\n- [Credit](https://github.com/joeyagreco/leeger#credit)\r\n\r\n## Overview\r\n\r\n![](https://github.com/joeyagreco/leeger/blob/main/img/leeger-overview-transparent.png)\r\nThis library allows you to take data from an existing fantasy football league and get instant stats from that league\r\ninto either a Python script or an Excel spreadsheet.\\\r\n\\\r\nThis library supports multiple fantasy sites AND manual league data input.\\\r\n\\\r\nPython stats will be stored in these objects:\r\n\r\n- [AllTimeStatSheet](https://github.com/joeyagreco/leeger/blob/main/leeger/model/stat/AllTimeStatSheet.py)\r\n- [YearStatSheet](https://github.com/joeyagreco/leeger/blob/main/leeger/model/stat/YearStatSheet.py)\r\n\r\nExcel sheets will include:\r\n\r\n- A tab for each year with team stats\r\n- A tab for each year with matchup info\r\n- A tab for all-time with team stats\r\n- A tab for all-time with matchup info\r\n- A tab for all-time with owner stats\r\n\r\n\\\r\nThe main idea behind this library is:\r\n\r\n1. Load stats into a League object\r\n2. Pass this League object into various library methods to extract stats\r\n\r\n\\\r\nFor guides on how to use this library, see the information\r\nunder [Supported League Loaders](https://github.com/joeyagreco/leeger#supported-league-loaders) and\r\nin the [`example`](https://github.com/joeyagreco/leeger/tree/main/example) folder.\r\n\r\n## Quickstart Guide\r\n\r\n#### 1. Download Python\r\n\r\n- Download the latest _supported_ version of Python [here](https://www.python.org/downloads/release/python-3109/).\r\n- Currently, Python version 3.10+ is supported\r\n\r\n#### 2. Create a basic Python file to use this library\r\n\r\n- Create a file that ends in the extension \".py\"\r\n   - Example: _my_script.py_\r\n\r\n#### 3. Download this library\r\n\r\n- Navigate in your terminal to the directory where you created your Python script in Step 2\r\n- Run the command `pip install leeger`\r\n   - If you do not have [pip](https://pip.pypa.io/en/stable/) installed, you will need to install it\r\n\r\n#### 4. Download your league data using a league loader\r\n\r\n- Find the site/s you use for fantasy football [here](https://github.com/joeyagreco/leeger#supported-league-loaders)\r\n- Follow the **Setup Documentation**\r\n- Once you have everything you need for your selected site/s, use the code examples\r\n  found [here](https://github.com/joeyagreco/leeger/tree/main/example/league_loader) for your specific site/s to\r\n  download your league data\r\n   - You can put the code inside the Python script you created in Step 2\r\n- If you have leagues that are continued in multiple sites, you can pull from multiple sites and add the League objects\r\n  together to combine the different sites\r\n   - An example of this can be\r\n     found [here](https://github.com/joeyagreco/leeger/blob/main/example/league/combiningLeagues.py)\r\n\r\n#### 5. Run your script\r\n\r\n- Navigate in your terminal to the directory where you created your Python script in Step 2\r\n- Run the command `py my_script.py`\r\n   - Replace _my_script.py_ with whatever you named your script in Step 2\r\n\r\n#### 6. Load your league stats into Excel\r\n\r\n- Slightly alter your script from Step 2 to include a function call to load your league stats into Excel\r\n- Follow [this example](https://github.com/joeyagreco/leeger/blob/main/example/stat/statsToExcelExample.py)\r\n- Make sure that you are passing the League object that you pulled from the league loader/s into the function call to\r\n  put your stats into Excel\r\n\r\n## FAQ\r\n\r\n**Question:**\r\nI'm getting this error when I run my script:\r\n<!---\r\n// @formatter:off\r\n-->\r\n```python3\r\nTypeError: dataclass() got an unexpected keyword argument 'kw_only'\r\n```\r\n<!---\r\n// @formatter:on\r\n-->\r\n\r\n**Answer:**\r\nThis error occurs when the Python version you are using is not 3.10 or greater.\\\r\nMake sure you are using Python version 3.10 or a newer version.\r\n\r\n**Q:**\r\nHow do I use this library to pull stats from my online fantasy league?\r\n\r\n**A:**\r\n\r\n1. Find your fantasy site [here](https://github.com/joeyagreco/leeger#supported-league-loaders) and ensure you have\r\n   everything you need for the site you are using\r\n2. Follow the [example code snippets](https://github.com/joeyagreco/leeger/tree/main/example/league_loader) for your\r\n   fantasy site to load the League object\r\n\r\n___\r\n**Q:**\r\nHow can I get stats into Excel once I have my League object?\r\n\r\n**A:**\r\nFollow [this example code](https://github.com/joeyagreco/leeger/blob/main/example/stat/statsToExcelExample.py).\r\n___\r\n**Q:**\r\nCan I combine years from different fantasy sites that are loaded as separate League objects into a single League object?\r\n\r\n**A:**\r\nYes, the League object supports addition (+) to combine multiple league objects.\\\r\nAn example of this can be\r\nfound [here](https://github.com/joeyagreco/leeger/blob/main/example/league/combiningLeagues.py).\r\n___\r\n**Q:**\r\nCan I disable validation on my League object?\r\n\r\n**A:**\r\nYes. While it is not recommended that you disable this, as validation ensures the stats are calculated properly,\r\ndisabling validation can be done by passing `validate=False` into any method that takes a League object.\r\n\r\n## Installation\r\n\r\nUse the package manager [pip](https://pip.pypa.io/en/stable/) to install.\r\n\r\n```bash\r\npip install leeger\r\n```\r\n\r\n## Supported League Loaders\r\n\r\nSites that you can automatically load your league data from.\r\n\r\n| Name            | Website                                   | Supported          | Setup Documentation                                                                                                       |\r\n|-----------------|-------------------------------------------|--------------------|---------------------------------------------------------------------------------------------------------------------------|\r\n| ESPN            | https://www.espn.com/fantasy/football/    | :heavy_check_mark: | [ESPN :page_facing_up:](https://github.com/joeyagreco/leeger/blob/main/doc/league_loader/espn.md)                         |\r\n| Fleaflicker     | https://www.fleaflicker.com/              | :heavy_check_mark: | [Fleaflicker :page_facing_up:](https://github.com/joeyagreco/leeger/blob/main/doc/league_loader/fleaflicker.md)           |  \r\n| MyFantasyLeague | http://home.myfantasyleague.com/          | :heavy_check_mark: | [MyFantasyLeague :page_facing_up:](https://github.com/joeyagreco/leeger/blob/main/doc/league_loader/my_fantasy_league.md) |\r\n| NFL             | https://fantasy.nfl.com/                  | :x:                | :x:                                                                                                                       |\r\n| Sleeper         | https://sleeper.com/fantasy-football/     | :heavy_check_mark: | [Sleeper :page_facing_up:](https://github.com/joeyagreco/leeger/blob/main/doc/league_loader/sleeper.md)                   |\r\n| Yahoo           | https://football.fantasysports.yahoo.com/ | :heavy_check_mark: | [Yahoo :page_facing_up:](https://github.com/joeyagreco/leeger/blob/main/doc/league_loader/yahoo.md)                       |\r\n<!---\r\n// @formatter:off\r\n-->\r\nIf a fantasy site you use is not listed here and you would like it to be, please [open an issue](https://github.com/joeyagreco/leeger/issues/new/choose).\r\n<!---\r\n// @formatter:on\r\n-->\r\n\r\n## Stats Explained\r\n\r\nStats used in this library are\r\ndocumented [here](https://github.com/joeyagreco/leeger/blob/main/doc/stats.md).\r\n\r\n## Running Tests\r\n\r\nTo run tests, run the following command:\r\n\r\n```bash\r\n  pytest\r\n```\r\n\r\n## Contributing\r\n\r\nPull requests are welcome. For major changes, please open an issue first to discuss what you would like to change.\r\n\r\nPlease make sure to update tests as appropriate.\r\n\r\n## License\r\n\r\n[MIT](https://choosealicense.com/licenses/mit/)\r\n\r\n## Credit\r\n\r\n- [ESPN API](https://github.com/cwendt94/espn-api)\r\n- [ESPN Private Leagues](https://cran.r-project.org/web/packages/ffscrapr/vignettes/espn_authentication.html)\r\n- [fleaflicker](https://github.com/joeyagreco/fleaflicker)\r\n- [pymfl](https://github.com/joeyagreco/pymfl)\r\n- [sleeper](https://github.com/joeyagreco/sleeper)\r\n- [YahooFantasy](https://github.com/mattdodge/yahoofantasy)\r\n",
    "description_content_type": "text/markdown",
    "docs_url": null,
    "download_url": "",
    "downloads": {
      "last_day": -1,
      "last_month": -1,
      "last_week": -1
    },
    "home_page": "https://github.com/joeyagreco/leeger",
    "keywords": "nfl statistics stats football espn yahoo sleeper myfantasyleague,fleaflicker",
    "license": "MIT",
    "maintainer": "",
    "maintainer_email": "",
    "name": "leeger",
    "package_url": "https://pypi.org/project/leeger/",
    "platform": null,
    "project_url": "https://pypi.org/project/leeger/",
    "project_urls": {
      "Homepage": "https://github.com/joeyagreco/leeger"
    },
    "release_url": "https://pypi.org/project/leeger/2.1.0/",
    "requires_dist": null,
    "requires_python": ">=3.10",
    "summary": "Instant stats for your fantasy football league.",
    "version": "2.1.0",
    "yanked": false,
    "yanked_reason": null
  },
  "last_serial": 17076607,
  "releases": {
    "0.1.0": [
      {
        "comment_text": "",
        "digests": {
          "blake2b_256": "044f0d96b9d7fa694f4a598bdc7c16c0bf50c70d2902ba977abea59fbbbb51ec",
          "md5": "7582b2b1e81336363847894a3f92ee47",
          "sha256": "f62fc0d176120f49f113d4c504e7b0a7a03c6d6e8bbd87b180f52b337929a1c9"
        },
        "downloads": -1,
        "filename": "leeger-0.1.0.tar.gz",
        "has_sig": false,
        "md5_digest": "7582b2b1e81336363847894a3f92ee47",
        "packagetype": "sdist",
        "python_version": "source",
        "requires_python": null,
        "size": 67362,
        "upload_time": "2022-07-13T01:41:57",
        "upload_time_iso_8601": "2022-07-13T01:41:57.797587Z",
        "url": "https://files.pythonhosted.org/packages/04/4f/0d96b9d7fa694f4a598bdc7c16c0bf50c70d2902ba977abea59fbbbb51ec/leeger-0.1.0.tar.gz",
        "yanked": false,
        "yanked_reason": null
      }
    ],
    "0.10.0": [
      {
        "comment_text": "",
        "digests": {
          "blake2b_256": "f1bc276aed928707e313e842c865f023800c0f1dcea92b3f923cd5ecb37f2e66",
          "md5": "cdaf2b6192b73e937b550fb25eb559c4",
          "sha256": "b685656fab0efeddbd233e4078e2eef807f32bd50144be244d12a1cdd623ca0a"
        },
        "downloads": -1,
        "filename": "leeger-0.10.0.tar.gz",
        "has_sig": false,
        "md5_digest": "cdaf2b6192b73e937b550fb25eb559c4",
        "packagetype": "sdist",
        "python_version": "source",
        "requires_python": null,
        "size": 81379,
        "upload_time": "2022-08-08T04:54:26",
        "upload_time_iso_8601": "2022-08-08T04:54:26.064965Z",
        "url": "https://files.pythonhosted.org/packages/f1/bc/276aed928707e313e842c865f023800c0f1dcea92b3f923cd5ecb37f2e66/leeger-0.10.0.tar.gz",
        "yanked": false,
        "yanked_reason": null
      }
    ],
    "0.11.0": [
      {
        "comment_text": "",
        "digests": {
          "blake2b_256": "b56e9166966172a7438f2659d9af9aaefc483250f2745ddadb7fffae5e0cfe22",
          "md5": "d0cab6d24aae415e94eafd38db991b0f",
          "sha256": "dac093ccc5c06891ec4ce4ca62c675b3c911fd8a949f21229cc879f75368c401"
        },
        "downloads": -1,
        "filename": "leeger-0.11.0.tar.gz",
        "has_sig": false,
        "md5_digest": "d0cab6d24aae415e94eafd38db991b0f",
        "packagetype": "sdist",
        "python_version": "source",
        "requires_python": null,
        "size": 80656,
        "upload_time": "2022-08-08T05:14:19",
        "upload_time_iso_8601": "2022-08-08T05:14:19.212259Z",
        "url": "https://files.pythonhosted.org/packages/b5/6e/9166966172a7438f2659d9af9aaefc483250f2745ddadb7fffae5e0cfe22/leeger-0.11.0.tar.gz",
        "yanked": false,
        "yanked_reason": null
      }
    ],
    "0.12.0": [
      {
        "comment_text": "",
        "digests": {
          "blake2b_256": "c519ca16c6578395c7bc5094ddb35931a603433426cd13ab6ff2a1d80e188ad8",
          "md5": "eb36dc1f4d01e33120222e805a20c0c9",
          "sha256": "d8048c55c6446c931a0d5a93a3e6bf5583584809971685c12787078cc3ac7b26"
        },
        "downloads": -1,
        "filename": "leeger-0.12.0.tar.gz",
        "has_sig": false,
        "md5_digest": "eb36dc1f4d01e33120222e805a20c0c9",
        "packagetype": "sdist",
        "python_version": "source",
        "requires_python": null,
        "size": 83231,
        "upload_time": "2022-08-09T00:40:28",
        "upload_time_iso_8601": "2022-08-09T00:40:28.514780Z",
        "url": "https://files.pythonhosted.org/packages/c5/19/ca16c6578395c7bc5094ddb35931a603433426cd13ab6ff2a1d80e188ad8/leeger-0.12.0.tar.gz",
        "yanked": false,
        "yanked_reason": null
      }
    ],
    "0.13.0": [
      {
        "comment_text": "",
        "digests": {
          "blake2b_256": "6f0709cb5def35ad1fc1a8f77448f1498bd8aafb76e105b38187c03bb9596475",
          "md5": "ba6a13ee1314ab5119bf8d72e3d02ad1",
          "sha256": "52013dcf7d5ebf94db49f1a960727fbc87df835026f23ef51af5a865ad99013a"
        },
        "downloads": -1,
        "filename": "leeger-0.13.0.tar.gz",
        "has_sig": false,
        "md5_digest": "ba6a13ee1314ab5119bf8d72e3d02ad1",
        "packagetype": "sdist",
        "python_version": "source",
        "requires_python": null,
        "size": 83270,
        "upload_time": "2022-08-09T00:44:45",
        "upload_time_iso_8601": "2022-08-09T00:44:45.457283Z",
        "url": "https://files.pythonhosted.org/packages/6f/07/09cb5def35ad1fc1a8f77448f1498bd8aafb76e105b38187c03bb9596475/leeger-0.13.0.tar.gz",
        "yanked": false,
        "yanked_reason": null
      }
    ],
    "0.14.0": [
      {
        "comment_text": "",
        "digests": {
          "blake2b_256": "e0f9b47bc29037f9afbb3c16121c8fb5f164cfd393941fad0709122c99d1053a",
          "md5": "0cdb2dde84bc8e0aa7c5cca1860139fe",
          "sha256": "de23955c26b56b6862261ccc7cd8a6fac7e0ce7d520db5abae006ccea2f5389a"
        },
        "downloads": -1,
        "filename": "leeger-0.14.0.tar.gz",
        "has_sig": false,
        "md5_digest": "0cdb2dde84bc8e0aa7c5cca1860139fe",
        "packagetype": "sdist",
        "python_version": "source",
        "requires_python": null,
        "size": 83327,
        "upload_time": "2022-08-09T22:04:29",
        "upload_time_iso_8601": "2022-08-09T22:04:29.173446Z",
        "url": "https://files.pythonhosted.org/packages/e0/f9/b47bc29037f9afbb3c16121c8fb5f164cfd393941fad0709122c99d1053a/leeger-0.14.0.tar.gz",
        "yanked": false,
        "yanked_reason": null
      }
    ],
    "0.15.0": [
      {
        "comment_text": "",
        "digests": {
          "blake2b_256": "426e98bbbde1dba3ccb4614c7ad22a1cc18baa6dfc89a7be7009636eceaedbd0",
          "md5": "e9ed7174d7bba7c17ea7d9a4b42a91e4",
          "sha256": "e94e2cc65e3def9227baf2fd38ee6c6c846dac7054976270ff339bb6d9428cd9"
        },
        "downloads": -1,
        "filename": "leeger-0.15.0.tar.gz",
        "has_sig": false,
        "md5_digest": "e9ed7174d7bba7c17ea7d9a4b42a91e4",
        "packagetype": "sdist",
        "python_version": "source",
        "requires_python": null,
        "size": 76233,
        "upload_time": "2022-08-13T05:35:47",
        "upload_time_iso_8601": "2022-08-13T05:35:47.346822Z",
        "url": "https://files.pythonhosted.org/packages/42/6e/98bbbde1dba3ccb4614c7ad22a1cc18baa6dfc89a7be7009636eceaedbd0/leeger-0.15.0.tar.gz",
        "yanked": false,
        "yanked_reason": null
      }
    ],
    "0.16.0": [
      {
        "comment_text": "",
        "digests": {
          "blake2b_256": "1401596220b24fcaa19489c12d0835277904384124ddf51ca8d7195df34f4dce",
          "md5": "328396eb49e382b4c7c42c7cef79d1dc",
          "sha256": "ef1d278bd5c82b0e1ab4e1cd905c2ba531bf3d8b34db5560470ede351f298f32"
        },
        "downloads": -1,
        "filename": "leeger-0.16.0.tar.gz",
        "has_sig": false,
        "md5_digest": "328396eb49e382b4c7c42c7cef79d1dc",
        "packagetype": "sdist",
        "python_version": "source",
        "requires_python": null,
        "size": 77039,
        "upload_time": "2022-08-13T05:44:19",
        "upload_time_iso_8601": "2022-08-13T05:44:19.338642Z",
        "url": "https://files.pythonhosted.org/packages/14/01/596220b24fcaa19489c12d0835277904384124ddf51ca8d7195df34f4dce/leeger-0.16.0.tar.gz",
        "yanked": false,
        "yanked_reason": null
      }
    ],
    "0.17.0": [
      {
        "comment_text": "",
        "digests": {
          "blake2b_256": "121d5460b98a0925629eb59b6cc6f00d8f30d7543a73abcfbd3ac8c185400c34",
          "md5": "43df4bc10d94a8a7bffe413999730b78",
          "sha256": "a4d73170fe5dbeb099ebbd67eb435ff175adc443f4b70b51596bbe0cbb989cd4"
        },
        "downloads": -1,
        "filename": "leeger-0.17.0.tar.gz",
        "has_sig": false,
        "md5_digest": "43df4bc10d94a8a7bffe413999730b78",
        "packagetype": "sdist",
        "python_version": "source",
        "requires_python": null,
        "size": 79439,
        "upload_time": "2022-08-13T05:58:33",
        "upload_time_iso_8601": "2022-08-13T05:58:33.710365Z",
        "url": "https://files.pythonhosted.org/packages/12/1d/5460b98a0925629eb59b6cc6f00d8f30d7543a73abcfbd3ac8c185400c34/leeger-0.17.0.tar.gz",
        "yanked": false,
        "yanked_reason": null
      }
    ],
    "0.18.0": [
      {
        "comment_text": "",
        "digests": {
          "blake2b_256": "166bbe4b1e85e22596fb32681313d0968a870135975230203db8cb66d2410041",
          "md5": "a23f010ecce625bd7a45b85884f7be3e",
          "sha256": "dcc5cec749b28fbf89d74df3f4519f597dd74f88794f3e3a598aef08fdf349fe"
        },
        "downloads": -1,
        "filename": "leeger-0.18.0.tar.gz",
        "has_sig": false,
        "md5_digest": "a23f010ecce625bd7a45b85884f7be3e",
        "packagetype": "sdist",
        "python_version": "source",
        "requires_python": null,
        "size": 82940,
        "upload_time": "2022-08-13T06:03:07",
        "upload_time_iso_8601": "2022-08-13T06:03:07.001202Z",
        "url": "https://files.pythonhosted.org/packages/16/6b/be4b1e85e22596fb32681313d0968a870135975230203db8cb66d2410041/leeger-0.18.0.tar.gz",
        "yanked": false,
        "yanked_reason": null
      }
    ],
    "0.2.0": [
      {
        "comment_text": "",
        "digests": {
          "blake2b_256": "7ddc52f23229422f4b22916af07a5212d05b5ee3d668c8f37776a1d93d13ebe6",
          "md5": "f4b38a77a559c356d3effc89a4b1a888",
          "sha256": "02b5a88f3b08e7b4f40cd1252902bdb1761306a2b34210289991291183428b16"
        },
        "downloads": -1,
        "filename": "leeger-0.2.0.tar.gz",
        "has_sig": false,
        "md5_digest": "f4b38a77a559c356d3effc89a4b1a888",
        "packagetype": "sdist",
        "python_version": "source",
        "requires_python": null,
        "size": 67569,
        "upload_time": "2022-07-13T02:40:40",
        "upload_time_iso_8601": "2022-07-13T02:40:40.827169Z",
        "url": "https://files.pythonhosted.org/packages/7d/dc/52f23229422f4b22916af07a5212d05b5ee3d668c8f37776a1d93d13ebe6/leeger-0.2.0.tar.gz",
        "yanked": false,
        "yanked_reason": null
      }
    ],
    "0.3.0": [
      {
        "comment_text": "",
        "digests": {
          "blake2b_256": "5dc250b4eec78c631d37e567fedb218dcb158ab09f9c96ffcbe1d5601f03aa74",
          "md5": "0660ccd9b82107556a4f7f2879610bdc",
          "sha256": "9ecccb9016f9ad953f38d08d4cd522a10b6a4cb26c348db690a477f3ee3b682b"
        },
        "downloads": -1,
        "filename": "leeger-0.3.0.tar.gz",
        "has_sig": false,
        "md5_digest": "0660ccd9b82107556a4f7f2879610bdc",
        "packagetype": "sdist",
        "python_version": "source",
        "requires_python": null,
        "size": 67711,
        "upload_time": "2022-07-21T04:21:49",
        "upload_time_iso_8601": "2022-07-21T04:21:49.139445Z",
        "url": "https://files.pythonhosted.org/packages/5d/c2/50b4eec78c631d37e567fedb218dcb158ab09f9c96ffcbe1d5601f03aa74/leeger-0.3.0.tar.gz",
        "yanked": false,
        "yanked_reason": null
      }
    ],
    "0.4.0": [
      {
        "comment_text": "",
        "digests": {
          "blake2b_256": "1ae0d58735f7e0539ab8d9166bdf305e6abdf84ef386435a82b2d98bc9bb7186",
          "md5": "9b6ac13c84405ed38d2cc6800fb7f450",
          "sha256": "54ef8475b8dc02b4eb8c0d10d713a503b1c5b9ab0e8606b0a2dcb831fd608977"
        },
        "downloads": -1,
        "filename": "leeger-0.4.0.tar.gz",
        "has_sig": false,
        "md5_digest": "9b6ac13c84405ed38d2cc6800fb7f450",
        "packagetype": "sdist",
        "python_version": "source",
        "requires_python": null,
        "size": 69114,
        "upload_time": "2022-07-25T22:31:47",
        "upload_time_iso_8601": "2022-07-25T22:31:47.236176Z",
        "url": "https://files.pythonhosted.org/packages/1a/e0/d58735f7e0539ab8d9166bdf305e6abdf84ef386435a82b2d98bc9bb7186/leeger-0.4.0.tar.gz",
        "yanked": false,
        "yanked_reason": null
      }
    ],
    "0.5.0": [
      {
        "comment_text": "",
        "digests": {
          "blake2b_256": "00c99a4a95b262a224253812c3ddf7d520ea648c63d9e00e458ca6715e644253",
          "md5": "b9cfc8b0b55ea2b34f04e0b8dce8dbeb",
          "sha256": "46d9ca5c8b383717d60e178c2d2bc4b0d771d137c96a2cbee6461418e449fd6d"
        },
        "downloads": -1,
        "filename": "leeger-0.5.0.tar.gz",
        "has_sig": false,
        "md5_digest": "b9cfc8b0b55ea2b34f04e0b8dce8dbeb",
        "packagetype": "sdist",
        "python_version": "source",
        "requires_python": null,
        "size": 69383,
        "upload_time": "2022-07-29T19:02:22",
        "upload_time_iso_8601": "2022-07-29T19:02:22.469208Z",
        "url": "https://files.pythonhosted.org/packages/00/c9/9a4a95b262a224253812c3ddf7d520ea648c63d9e00e458ca6715e644253/leeger-0.5.0.tar.gz",
        "yanked": false,
        "yanked_reason": null
      }
    ],
    "0.6.0": [
      {
        "comment_text": "",
        "digests": {
          "blake2b_256": "901de9137a743646ba75459a5f33d6097f560bd69ef0a17dfe9474ee3324ba7e",
          "md5": "a5f470adc25d5c35747e83e80515c8f7",
          "sha256": "71431a7ff1e399145d09ef6b0985279cd7e7f0d2ba33f3ccf209afa79675377f"
        },
        "downloads": -1,
        "filename": "leeger-0.6.0.tar.gz",
        "has_sig": false,
        "md5_digest": "a5f470adc25d5c35747e83e80515c8f7",
        "packagetype": "sdist",
        "python_version": "source",
        "requires_python": null,
        "size": 69371,
        "upload_time": "2022-07-29T19:05:37",
        "upload_time_iso_8601": "2022-07-29T19:05:37.461550Z",
        "url": "https://files.pythonhosted.org/packages/90/1d/e9137a743646ba75459a5f33d6097f560bd69ef0a17dfe9474ee3324ba7e/leeger-0.6.0.tar.gz",
        "yanked": false,
        "yanked_reason": null
      }
    ],
    "0.7.0": [
      {
        "comment_text": "",
        "digests": {
          "blake2b_256": "c8d0eb2a07ddbf8035c7d528420091a3484a649b18a187c997619df9498df911",
          "md5": "4326cadebb5552d33513c5e041d075f7",
          "sha256": "794ef916d11d6720e7e9179b9d502f436f8252a03b3ad41b5a178763fbd7029f"
        },
        "downloads": -1,
        "filename": "leeger-0.7.0.tar.gz",
        "has_sig": false,
        "md5_digest": "4326cadebb5552d33513c5e041d075f7",
        "packagetype": "sdist",
        "python_version": "source",
        "requires_python": null,
        "size": 69401,
        "upload_time": "2022-07-30T00:14:24",
        "upload_time_iso_8601": "2022-07-30T00:14:24.947807Z",
        "url": "https://files.pythonhosted.org/packages/c8/d0/eb2a07ddbf8035c7d528420091a3484a649b18a187c997619df9498df911/leeger-0.7.0.tar.gz",
        "yanked": false,
        "yanked_reason": null
      }
    ],
    "0.8.0": [
      {
        "comment_text": "",
        "digests": {
          "blake2b_256": "aeb03543a8e817aabd7687bf7135ee161e5ba4256e939e2c5e3cdb92072cc377",
          "md5": "cfacc850cad9cb8ec04d3e0bd27491e1",
          "sha256": "4332d8865f628bfadbbdf26ee278951063722afb8aece187057a49ddbb78790e"
        },
        "downloads": -1,
        "filename": "leeger-0.8.0.tar.gz",
        "has_sig": false,
        "md5_digest": "cfacc850cad9cb8ec04d3e0bd27491e1",
        "packagetype": "sdist",
        "python_version": "source",
        "requires_python": null,
        "size": 71402,
        "upload_time": "2022-07-30T05:49:21",
        "upload_time_iso_8601": "2022-07-30T05:49:21.176347Z",
        "url": "https://files.pythonhosted.org/packages/ae/b0/3543a8e817aabd7687bf7135ee161e5ba4256e939e2c5e3cdb92072cc377/leeger-0.8.0.tar.gz",
        "yanked": false,
        "yanked_reason": null
      }
    ],
    "0.9.0": [
      {
        "comment_text": "",
        "digests": {
          "blake2b_256": "0f523cc676867ce44995a6fb2af710eaa9cf9723399465e56fac6d76563a2f03",
          "md5": "807a154f440dd93bec952f074d9b9244",
          "sha256": "ba4c9c1c67c561122a6882c0327b64f7e523c1c60c24ab3cafc8a4fba566b3ee"
        },
        "downloads": -1,
        "filename": "leeger-0.9.0.tar.gz",
        "has_sig": false,
        "md5_digest": "807a154f440dd93bec952f074d9b9244",
        "packagetype": "sdist",
        "python_version": "source",
        "requires_python": null,
        "size": 81018,
        "upload_time": "2022-08-03T23:29:34",
        "upload_time_iso_8601": "2022-08-03T23:29:34.381589Z",
        "url": "https://files.pythonhosted.org/packages/0f/52/3cc676867ce44995a6fb2af710eaa9cf9723399465e56fac6d76563a2f03/leeger-0.9.0.tar.gz",
        "yanked": false,
        "yanked_reason": null
      }
    ],
    "1.0.0": [
      {
        "comment_text": "",
        "digests": {
          "blake2b_256": "4b320b6a13aa70f487f522a9c84e22b4d24ba20dce292c52975483862097036a",
          "md5": "e773d1accf45faf12d495b57f015694e",
          "sha256": "c0b03a05d737d1e040e2d8f669b3baf034fb285a44e49a2e8fe6fdf7b286c209"
        },
        "downloads": -1,
        "filename": "leeger-1.0.0.tar.gz",
        "has_sig": false,
        "md5_digest": "e773d1accf45faf12d495b57f015694e",
        "packagetype": "sdist",
        "python_version": "source",
        "requires_python": null,
        "size": 84020,
        "upload_time": "2022-09-03T02:00:21",
        "upload_time_iso_8601": "2022-09-03T02:00:21.804436Z",
        "url": "https://files.pythonhosted.org/packages/4b/32/0b6a13aa70f487f522a9c84e22b4d24ba20dce292c52975483862097036a/leeger-1.0.0.tar.gz",
        "yanked": false,
        "yanked_reason": null
      }
    ],
    "1.1.0": [
      {
        "comment_text": "",
        "digests": {
          "blake2b_256": "f8863adf7d06112c4537686cbf99e74603865bb39099984bf520376240fcd44b",
          "md5": "fd732a6773214bc7a5cda7fc8e23bf5e",
          "sha256": "a6ee974955c44e704dedc7a9827938e5b43971e94f4dcce7c71863e2661082a8"
        },
        "downloads": -1,
        "filename": "leeger-1.1.0.tar.gz",
        "has_sig": false,
        "md5_digest": "fd732a6773214bc7a5cda7fc8e23bf5e",
        "packagetype": "sdist",
        "python_version": "source",
        "requires_python": null,
        "size": 85466,
        "upload_time": "2022-09-03T21:53:24",
        "upload_time_iso_8601": "2022-09-03T21:53:24.260969Z",
        "url": "https://files.pythonhosted.org/packages/f8/86/3adf7d06112c4537686cbf99e74603865bb39099984bf520376240fcd44b/leeger-1.1.0.tar.gz",
        "yanked": false,
        "yanked_reason": null
      }
    ],
    "1.1.1": [
      {
        "comment_text": "",
        "digests": {
          "blake2b_256": "4d35aba64e7a71cdd823028c383ab328ba3e16d0aab68bfb7c33e0ba4611754a",
          "md5": "72eea22eefb0a4c473d9e411a8d4ccb9",
          "sha256": "164e5bfd04beef5837af21a6d2bc9d91941ffe66804531e666631cc220f9d2f3"
        },
        "downloads": -1,
        "filename": "leeger-1.1.1.tar.gz",
        "has_sig": false,
        "md5_digest": "72eea22eefb0a4c473d9e411a8d4ccb9",
        "packagetype": "sdist",
        "python_version": "source",
        "requires_python": null,
        "size": 85552,
        "upload_time": "2022-09-06T16:56:22",
        "upload_time_iso_8601": "2022-09-06T16:56:22.736466Z",
        "url": "https://files.pythonhosted.org/packages/4d/35/aba64e7a71cdd823028c383ab328ba3e16d0aab68bfb7c33e0ba4611754a/leeger-1.1.1.tar.gz",
        "yanked": false,
        "yanked_reason": null
      }
    ],
    "1.10.0": [
      {
        "comment_text": "",
        "digests": {
          "blake2b_256": "6874b3cb3a9d0a2dcb6cd8cca74c3167b49920d0b30ee5a4117e3f061328d567",
          "md5": "bad0f72b7c156248e568e9847037debe",
          "sha256": "e83661428696a2b28be7be094b3393801ece2294853b8407e8a59c8ebd2de327"
        },
        "downloads": -1,
        "filename": "leeger-1.10.0.tar.gz",
        "has_sig": false,
        "md5_digest": "bad0f72b7c156248e568e9847037debe",
        "packagetype": "sdist",
        "python_version": "source",
        "requires_python": ">=3.10",
        "size": 98294,
        "upload_time": "2022-11-01T16:04:20",
        "upload_time_iso_8601": "2022-11-01T16:04:20.499235Z",
        "url": "https://files.pythonhosted.org/packages/68/74/b3cb3a9d0a2dcb6cd8cca74c3167b49920d0b30ee5a4117e3f061328d567/leeger-1.10.0.tar.gz",
        "yanked": false,
        "yanked_reason": null
      }
    ],
    "1.11.0": [
      {
        "comment_text": "",
        "digests": {
          "blake2b_256": "ab6401475e54179dc728d43652bfcd7a9b3703efc6b26966df1f99ad15c5c91e",
          "md5": "e7683fb7e8397b2d2d61685d0b797f16",
          "sha256": "c29b45d584ae9f59668e2d1571e4cb403133221e86a61690aca6d4773c6d5f2a"
        },
        "downloads": -1,
        "filename": "leeger-1.11.0.tar.gz",
        "has_sig": false,
        "md5_digest": "e7683fb7e8397b2d2d61685d0b797f16",
        "packagetype": "sdist",
        "python_version": "source",
        "requires_python": ">=3.10",
        "size": 98965,
        "upload_time": "2022-12-22T23:58:03",
        "upload_time_iso_8601": "2022-12-22T23:58:03.715379Z",
        "url": "https://files.pythonhosted.org/packages/ab/64/01475e54179dc728d43652bfcd7a9b3703efc6b26966df1f99ad15c5c91e/leeger-1.11.0.tar.gz",
        "yanked": false,
        "yanked_reason": null
      }
    ],
    "1.12.0": [
      {
        "comment_text": "",
        "digests": {
          "blake2b_256": "117f17930a5126c4a0f80e0bc85259fc86bdfe147e0d138ef725cc2e005a7ffd",
          "md5": "79a942630d697dabf30492fbc387a0a9",
          "sha256": "7c35b23d66eb2cf29f68b69ef9986cffa4dc7e9f4536c6ba01be9e37df18b803"
        },
        "downloads": -1,
        "filename": "leeger-1.12.0.tar.gz",
        "has_sig": false,
        "md5_digest": "79a942630d697dabf30492fbc387a0a9",
        "packagetype": "sdist",
        "python_version": "source",
        "requires_python": ">=3.10",
        "size": 104519,
        "upload_time": "2023-01-02T01:46:55",
        "upload_time_iso_8601": "2023-01-02T01:46:55.729494Z",
        "url": "https://files.pythonhosted.org/packages/11/7f/17930a5126c4a0f80e0bc85259fc86bdfe147e0d138ef725cc2e005a7ffd/leeger-1.12.0.tar.gz",
        "yanked": false,
        "yanked_reason": null
      }
    ],
    "1.12.1": [
      {
        "comment_text": "",
        "digests": {
          "blake2b_256": "f5a10be35e1c32fa094801685e44c400b175ea910cedcfa131cfb34b402495b8",
          "md5": "0aab18a8fdc73199bc338b5412bec40b",
          "sha256": "4b0b25a58897986ff357ea059d67570d53577cd9f15ac57ab4a98bb79388f2ad"
        },
        "downloads": -1,
        "filename": "leeger-1.12.1.tar.gz",
        "has_sig": false,
        "md5_digest": "0aab18a8fdc73199bc338b5412bec40b",
        "packagetype": "sdist",
        "python_version": "source",
        "requires_python": ">=3.10",
        "size": 104566,
        "upload_time": "2023-01-03T03:03:31",
        "upload_time_iso_8601": "2023-01-03T03:03:31.567714Z",
        "url": "https://files.pythonhosted.org/packages/f5/a1/0be35e1c32fa094801685e44c400b175ea910cedcfa131cfb34b402495b8/leeger-1.12.1.tar.gz",
        "yanked": false,
        "yanked_reason": null
      }
    ],
    "1.13.0": [
      {
        "comment_text": "",
        "digests": {
          "blake2b_256": "8c22832d0b34ee576f42657915b6406e16eb525c6cbda0bb811a6e95219606b6",
          "md5": "7bfca1ac9b11aa0a53b27af96381e0b6",
          "sha256": "8ce8b83319dfda13b2a1876c4caf66376be5aef5730961b7c673ad400db9d0fb"
        },
        "downloads": -1,
        "filename": "leeger-1.13.0.tar.gz",
        "has_sig": false,
        "md5_digest": "7bfca1ac9b11aa0a53b27af96381e0b6",
        "packagetype": "sdist",
        "python_version": "source",
        "requires_python": ">=3.10",
        "size": 107140,
        "upload_time": "2023-01-04T01:56:07",
        "upload_time_iso_8601": "2023-01-04T01:56:07.500849Z",
        "url": "https://files.pythonhosted.org/packages/8c/22/832d0b34ee576f42657915b6406e16eb525c6cbda0bb811a6e95219606b6/leeger-1.13.0.tar.gz",
        "yanked": false,
        "yanked_reason": null
      }
    ],
    "1.13.1": [
      {
        "comment_text": "",
        "digests": {
          "blake2b_256": "820fe31ac123ceff9a61f55f27427113fd40c16fa67efa56c171606933702d32",
          "md5": "74a3c6c3b309186722e084f376ced709",
          "sha256": "0d6f1216a2ba0cfbb7c8c603b96ed4230781215cb36ec9309f7ccc1073bf65a3"
        },
        "downloads": -1,
        "filename": "leeger-1.13.1.tar.gz",
        "has_sig": false,
        "md5_digest": "74a3c6c3b309186722e084f376ced709",
        "packagetype": "sdist",
        "python_version": "source",
        "requires_python": ">=3.10",
        "size": 107588,
        "upload_time": "2023-01-29T18:21:06",
        "upload_time_iso_8601": "2023-01-29T18:21:06.130830Z",
        "url": "https://files.pythonhosted.org/packages/82/0f/e31ac123ceff9a61f55f27427113fd40c16fa67efa56c171606933702d32/leeger-1.13.1.tar.gz",
        "yanked": false,
        "yanked_reason": null
      }
    ],
    "1.14.0": [
      {
        "comment_text": "",
        "digests": {
          "blake2b_256": "05b119172aeed6c3a6bda9081e4ac081cee2398c171427de1d68ad96805e850a",
          "md5": "41e65e6a6b40a78106ee7426156a1d8e",
          "sha256": "623e3ddd6c3a7f2b0f6ea9b2b2cee737ceb871dbaa9bdf6105c3f0864e49e3dc"
        },
        "downloads": -1,
        "filename": "leeger-1.14.0.tar.gz",
        "has_sig": false,
        "md5_digest": "41e65e6a6b40a78106ee7426156a1d8e",
        "packagetype": "sdist",
        "python_version": "source",
        "requires_python": ">=3.10",
        "size": 107537,
        "upload_time": "2023-02-16T17:08:28",
        "upload_time_iso_8601": "2023-02-16T17:08:28.547082Z",
        "url": "https://files.pythonhosted.org/packages/05/b1/19172aeed6c3a6bda9081e4ac081cee2398c171427de1d68ad96805e850a/leeger-1.14.0.tar.gz",
        "yanked": false,
        "yanked_reason": null
      }
    ],
    "1.15.0": [
      {
        "comment_text": "",
        "digests": {
          "blake2b_256": "efe5c03cb723b40214b5a0e173087371c68c3846b4cebe3d70e5870d81d68656",
          "md5": "b66ded4547da44b8a5b4f221f068e077",
          "sha256": "12ecb4f700757dca8999a0a884b120f20418fbe1aa3195c775b80d47743a7acb"
        },
        "downloads": -1,
        "filename": "leeger-1.15.0.tar.gz",
        "has_sig": false,
        "md5_digest": "b66ded4547da44b8a5b4f221f068e077",
        "packagetype": "sdist",
        "python_version": "source",
        "requires_python": ">=3.10",
        "size": 108555,
        "upload_time": "2023-02-17T19:39:18",
        "upload_time_iso_8601": "2023-02-17T19:39:18.025883Z",
        "url": "https://files.pythonhosted.org/packages/ef/e5/c03cb723b40214b5a0e173087371c68c3846b4cebe3d70e5870d81d68656/leeger-1.15.0.tar.gz",
        "yanked": false,
        "yanked_reason": null
      }
    ],
    "1.2.0": [
      {
        "comment_text": "",
        "digests": {
          "blake2b_256": "e14684633302c26d7a5ef91063c66d913567da3f4b39a88147b168800824f0b9",
          "md5": "16288901f784693e9f826c9abc495312",
          "sha256": "38fda1ab195754657dd6956e7dc8d20ef40e4af8604f5ab79944eec04ab192db"
        },
        "downloads": -1,
        "filename": "leeger-1.2.0.tar.gz",
        "has_sig": false,
        "md5_digest": "16288901f784693e9f826c9abc495312",
        "packagetype": "sdist",
        "python_version": "source",
        "requires_python": null,
        "size": 85597,
        "upload_time": "2022-09-13T21:54:07",
        "upload_time_iso_8601": "2022-09-13T21:54:07.932618Z",
        "url": "https://files.pythonhosted.org/packages/e1/46/84633302c26d7a5ef91063c66d913567da3f4b39a88147b168800824f0b9/leeger-1.2.0.tar.gz",
        "yanked": false,
        "yanked_reason": null
      }
    ],
    "1.3.0": [
      {
        "comment_text": "",
        "digests": {
          "blake2b_256": "91d7a36fa4b3e472cf88f958c6b326d3d1e23a32cdd24fb176138791503ca3c9",
          "md5": "bf9aa0b8060216ab68a571631da8833f",
          "sha256": "28cbde43e5bf242f9387afd3b3c2d5e87e2ab4a19299fc5f3b59b14e60ed7eb6"
        },
        "downloads": -1,
        "filename": "leeger-1.3.0.tar.gz",
        "has_sig": false,
        "md5_digest": "bf9aa0b8060216ab68a571631da8833f",
        "packagetype": "sdist",
        "python_version": "source",
        "requires_python": null,
        "size": 85738,
        "upload_time": "2022-09-13T23:07:13",
        "upload_time_iso_8601": "2022-09-13T23:07:13.318363Z",
        "url": "https://files.pythonhosted.org/packages/91/d7/a36fa4b3e472cf88f958c6b326d3d1e23a32cdd24fb176138791503ca3c9/leeger-1.3.0.tar.gz",
        "yanked": false,
        "yanked_reason": null
      }
    ],
    "1.3.1": [
      {
        "comment_text": "",
        "digests": {
          "blake2b_256": "2509748fb6df93f809d7173084ea5d60a095f3e5a4e7b88fb6d32eb524e383b3",
          "md5": "d9e02857b267f8dc8965a37dac457092",
          "sha256": "87844dc1b082df4bbd93984c2e9ac2bb359afa15162a17f5c55ab32a9d7eaf0d"
        },
        "downloads": -1,
        "filename": "leeger-1.3.1.tar.gz",
        "has_sig": false,
        "md5_digest": "d9e02857b267f8dc8965a37dac457092",
        "packagetype": "sdist",
        "python_version": "source",
        "requires_python": null,
        "size": 85718,
        "upload_time": "2022-09-13T23:25:34",
        "upload_time_iso_8601": "2022-09-13T23:25:34.335432Z",
        "url": "https://files.pythonhosted.org/packages/25/09/748fb6df93f809d7173084ea5d60a095f3e5a4e7b88fb6d32eb524e383b3/leeger-1.3.1.tar.gz",
        "yanked": false,
        "yanked_reason": null
      }
    ],
    "1.3.2": [
      {
        "comment_text": "",
        "digests": {
          "blake2b_256": "78b2921292f7c9c334635000ec61b157715edf4dafa4d8136bcf65d6b74bf134",
          "md5": "703dd8b20d2e6250834a97c20aa2bfba",
          "sha256": "2fecd2ddabdffeaf0179dad4cfab16cf417fabb4d64b509fe57b4ba12157579f"
        },
        "downloads": -1,
        "filename": "leeger-1.3.2.tar.gz",
        "has_sig": false,
        "md5_digest": "703dd8b20d2e6250834a97c20aa2bfba",
        "packagetype": "sdist",
        "python_version": "source",
        "requires_python": null,
        "size": 85798,
        "upload_time": "2022-09-15T23:18:18",
        "upload_time_iso_8601": "2022-09-15T23:18:18.534857Z",
        "url": "https://files.pythonhosted.org/packages/78/b2/921292f7c9c334635000ec61b157715edf4dafa4d8136bcf65d6b74bf134/leeger-1.3.2.tar.gz",
        "yanked": false,
        "yanked_reason": null
      }
    ],
    "1.3.3": [
      {
        "comment_text": "",
        "digests": {
          "blake2b_256": "1a6a4c729d434f10e1f502ec7149f6781a9dee359011d6419766a4a9790271ba",
          "md5": "b31b40f2bb4d6924515979afe7fb42de",
          "sha256": "298045ec195854c39086603ad836555b214dfa57963e0f4da78ca93e0e1e720b"
        },
        "downloads": -1,
        "filename": "leeger-1.3.3.tar.gz",
        "has_sig": false,
        "md5_digest": "b31b40f2bb4d6924515979afe7fb42de",
        "packagetype": "sdist",
        "python_version": "source",
        "requires_python": null,
        "size": 86376,
        "upload_time": "2022-09-17T17:21:20",
        "upload_time_iso_8601": "2022-09-17T17:21:20.272853Z",
        "url": "https://files.pythonhosted.org/packages/1a/6a/4c729d434f10e1f502ec7149f6781a9dee359011d6419766a4a9790271ba/leeger-1.3.3.tar.gz",
        "yanked": false,
        "yanked_reason": null
      }
    ],
    "1.4.0": [
      {
        "comment_text": "",
        "digests": {
          "blake2b_256": "dd14fddec9b9a9cc35a4507fd3969ab0b1f50fe87e6b91264efa64bc3a75f906",
          "md5": "e9b88efafaa7aa66edd0c9fd7ad5e801",
          "sha256": "bdfd6c57866ccc5bfecf9a70ae060481bc6d1171b0f75c7302c84671d128128d"
        },
        "downloads": -1,
        "filename": "leeger-1.4.0.tar.gz",
        "has_sig": false,
        "md5_digest": "e9b88efafaa7aa66edd0c9fd7ad5e801",
        "packagetype": "sdist",
        "python_version": "source",
        "requires_python": null,
        "size": 84108,
        "upload_time": "2022-09-17T18:38:23",
        "upload_time_iso_8601": "2022-09-17T18:38:23.337847Z",
        "url": "https://files.pythonhosted.org/packages/dd/14/fddec9b9a9cc35a4507fd3969ab0b1f50fe87e6b91264efa64bc3a75f906/leeger-1.4.0.tar.gz",
        "yanked": false,
        "yanked_reason": null
      }
    ],
    "1.4.1": [
      {
        "comment_text": "",
        "digests": {
          "blake2b_256": "4a19cd3953e8c2d1e897710de660af30779ac0b6ab0cea2a1b2e20f5a81a89db",
          "md5": "1620db4d13ae6b5dea2a076a5fbee71b",
          "sha256": "5119e8d2acc991f90298398be001ecfd8deb08a1d36e570542b1aaa3f0f7a93f"
        },
        "downloads": -1,
        "filename": "leeger-1.4.1.tar.gz",
        "has_sig": false,
        "md5_digest": "1620db4d13ae6b5dea2a076a5fbee71b",
        "packagetype": "sdist",
        "python_version": "source",
        "requires_python": null,
        "size": 84680,
        "upload_time": "2022-09-19T23:03:19",
        "upload_time_iso_8601": "2022-09-19T23:03:19.329775Z",
        "url": "https://files.pythonhosted.org/packages/4a/19/cd3953e8c2d1e897710de660af30779ac0b6ab0cea2a1b2e20f5a81a89db/leeger-1.4.1.tar.gz",
        "yanked": false,
        "yanked_reason": null
      }
    ],
    "1.5.0": [
      {
        "comment_text": "",
        "digests": {
          "blake2b_256": "c3e0943196c49c9e914b009856ecc6b1ad0aea05dc508855540edb42c781ce1f",
          "md5": "571b755904ca2acd973b3bb44fe5b70c",
          "sha256": "fa544778fb7a41869ca2355c73e04b03942f8121c026e43344e19a152964e4c0"
        },
        "downloads": -1,
        "filename": "leeger-1.5.0.tar.gz",
        "has_sig": false,
        "md5_digest": "571b755904ca2acd973b3bb44fe5b70c",
        "packagetype": "sdist",
        "python_version": "source",
        "requires_python": null,
        "size": 87725,
        "upload_time": "2022-09-20T23:00:59",
        "upload_time_iso_8601": "2022-09-20T23:00:59.638233Z",
        "url": "https://files.pythonhosted.org/packages/c3/e0/943196c49c9e914b009856ecc6b1ad0aea05dc508855540edb42c781ce1f/leeger-1.5.0.tar.gz",
        "yanked": false,
        "yanked_reason": null
      }
    ],
    "1.6.0": [
      {
        "comment_text": "",
        "digests": {
          "blake2b_256": "aa04e8bd2802d768dc6eb45d2a4b928b98cbcf2fef1eecd30a634044a7ff7bbb",
          "md5": "f146e6f3e8d2b0190c0357e8fa7c0b77",
          "sha256": "6ce7d6ee51837f462350f18c1066f2f67d45bae7d74a804d07c488579bdf5c5b"
        },
        "downloads": -1,
        "filename": "leeger-1.6.0.tar.gz",
        "has_sig": false,
        "md5_digest": "f146e6f3e8d2b0190c0357e8fa7c0b77",
        "packagetype": "sdist",
        "python_version": "source",
        "requires_python": ">=3.10",
        "size": 88814,
        "upload_time": "2022-10-10T18:33:34",
        "upload_time_iso_8601": "2022-10-10T18:33:34.054067Z",
        "url": "https://files.pythonhosted.org/packages/aa/04/e8bd2802d768dc6eb45d2a4b928b98cbcf2fef1eecd30a634044a7ff7bbb/leeger-1.6.0.tar.gz",
        "yanked": false,
        "yanked_reason": null
      }
    ],
    "1.6.1": [
      {
        "comment_text": "",
        "digests": {
          "blake2b_256": "284afc5ef2c83e2d52bf9ee3cdb6480e7ca93d193cf64eeb3fb9637b3f4d1548",
          "md5": "23b2c1384d696160f5e92a3710821001",
          "sha256": "e9562c0062bc07f7b498e0ec6e46da199d7983460463d0b29b884579bcc7d11f"
        },
        "downloads": -1,
        "filename": "leeger-1.6.1.tar.gz",
        "has_sig": false,
        "md5_digest": "23b2c1384d696160f5e92a3710821001",
        "packagetype": "sdist",
        "python_version": "source",
        "requires_python": ">=3.10",
        "size": 88827,
        "upload_time": "2022-10-11T02:20:12",
        "upload_time_iso_8601": "2022-10-11T02:20:12.873981Z",
        "url": "https://files.pythonhosted.org/packages/28/4a/fc5ef2c83e2d52bf9ee3cdb6480e7ca93d193cf64eeb3fb9637b3f4d1548/leeger-1.6.1.tar.gz",
        "yanked": false,
        "yanked_reason": null
      }
    ],
    "1.7.0": [
      {
        "comment_text": "",
        "digests": {
          "blake2b_256": "1f03582a6157e8e7822e0741395e75a342835827b0354554a30daf85b9c82cd3",
          "md5": "79d916bce398a36bfe3321eafba049f7",
          "sha256": "96d0b00ee001fed3d3597d430af73b6d9423e471826bc8e0f5e9d7ca7513b112"
        },
        "downloads": -1,
        "filename": "leeger-1.7.0.tar.gz",
        "has_sig": false,
        "md5_digest": "79d916bce398a36bfe3321eafba049f7",
        "packagetype": "sdist",
        "python_version": "source",
        "requires_python": ">=3.10",
        "size": 92506,
        "upload_time": "2022-10-16T01:36:42",
        "upload_time_iso_8601": "2022-10-16T01:36:42.251869Z",
        "url": "https://files.pythonhosted.org/packages/1f/03/582a6157e8e7822e0741395e75a342835827b0354554a30daf85b9c82cd3/leeger-1.7.0.tar.gz",
        "yanked": false,
        "yanked_reason": null
      }
    ],
    "1.8.0": [
      {
        "comment_text": "",
        "digests": {
          "blake2b_256": "cb279e4f0712104dafcecca89d28efa819aa2e3e39f728b3b922173ab65794ea",
          "md5": "fd6c4427acbe5c58cc33ee40bc658da8",
          "sha256": "5a8bb584fd855de9af77f7e1b6ff462f2ab946a23541ff6f1594975591908c8f"
        },
        "downloads": -1,
        "filename": "leeger-1.8.0.tar.gz",
        "has_sig": false,
        "md5_digest": "fd6c4427acbe5c58cc33ee40bc658da8",
        "packagetype": "sdist",
        "python_version": "source",
        "requires_python": ">=3.10",
        "size": 95026,
        "upload_time": "2022-10-18T22:00:14",
        "upload_time_iso_8601": "2022-10-18T22:00:14.756268Z",
        "url": "https://files.pythonhosted.org/packages/cb/27/9e4f0712104dafcecca89d28efa819aa2e3e39f728b3b922173ab65794ea/leeger-1.8.0.tar.gz",
        "yanked": false,
        "yanked_reason": null
      }
    ],
    "1.9.0": [
      {
        "comment_text": "",
        "digests": {
          "blake2b_256": "09c203e7527b48104dddb45142373c99ba72e67cadff392997b547243f08ead3",
          "md5": "2c75b4394d55ce06e169ae28652a9f44",
          "sha256": "2315ce07bc3e0814a5a1ce46c3a3f5c6f28808a2a93baec7aa49c01bef4079e8"
        },
        "downloads": -1,
        "filename": "leeger-1.9.0.tar.gz",
        "has_sig": false,
        "md5_digest": "2c75b4394d55ce06e169ae28652a9f44",
        "packagetype": "sdist",
        "python_version": "source",
        "requires_python": ">=3.10",
        "size": 96183,
        "upload_time": "2022-10-26T20:05:49",
        "upload_time_iso_8601": "2022-10-26T20:05:49.736049Z",
        "url": "https://files.pythonhosted.org/packages/09/c2/03e7527b48104dddb45142373c99ba72e67cadff392997b547243f08ead3/leeger-1.9.0.tar.gz",
        "yanked": false,
        "yanked_reason": null
      }
    ],
    "2.0.0": [
      {
        "comment_text": "",
        "digests": {
          "blake2b_256": "ce97d80d476eb5103c465a4e21455c35ca8996024bf6bcebf65822844c3f1a94",
          "md5": "15c5937116fdce3eee6346a6fb101762",
          "sha256": "a6e3074a3500c17ea012b1fb5e1a52726d38008b354fb7bd8e2ef9ade8749f81"
        },
        "downloads": -1,
        "filename": "leeger-2.0.0.tar.gz",
        "has_sig": false,
        "md5_digest": "15c5937116fdce3eee6346a6fb101762",
        "packagetype": "sdist",
        "python_version": "source",
        "requires_python": ">=3.10",
        "size": 108386,
        "upload_time": "2023-02-18T07:10:37",
        "upload_time_iso_8601": "2023-02-18T07:10:37.264719Z",
        "url": "https://files.pythonhosted.org/packages/ce/97/d80d476eb5103c465a4e21455c35ca8996024bf6bcebf65822844c3f1a94/leeger-2.0.0.tar.gz",
        "yanked": false,
        "yanked_reason": null
      }
    ],
    "2.1.0": [
      {
        "comment_text": "",
        "digests": {
          "blake2b_256": "18ef5dd8d1cc78fdc8c3d339b656a845fa7ac43c5327710775d08218a90e831a",
          "md5": "fdfeaca51294c5ae3cb5f80e47f26014",
          "sha256": "4b9fe9ef0dca99db21144cf8a8194322984c81c96b2766e5f314f46dea87d3bf"
        },
        "downloads": -1,
        "filename": "leeger-2.1.0.tar.gz",
        "has_sig": false,
        "md5_digest": "fdfeaca51294c5ae3cb5f80e47f26014",
        "packagetype": "sdist",
        "python_version": "source",
        "requires_python": ">=3.10",
        "size": 108650,
        "upload_time": "2023-02-28T02:37:04",
        "upload_time_iso_8601": "2023-02-28T02:37:04.960343Z",
        "url": "https://files.pythonhosted.org/packages/18/ef/5dd8d1cc78fdc8c3d339b656a845fa7ac43c5327710775d08218a90e831a/leeger-2.1.0.tar.gz",
        "yanked": false,
        "yanked_reason": null
      }
    ]
  },
  "urls": [
    {
      "comment_text": "",
      "digests": {
        "blake2b_256": "18ef5dd8d1cc78fdc8c3d339b656a845fa7ac43c5327710775d08218a90e831a",
        "md5": "fdfeaca51294c5ae3cb5f80e47f26014",
        "sha256": "4b9fe9ef0dca99db21144cf8a8194322984c81c96b2766e5f314f46dea87d3bf"
      },
      "downloads": -1,
      "filename": "leeger-2.1.0.tar.gz",
      "has_sig": false,
      "md5_digest": "fdfeaca51294c5ae3cb5f80e47f26014",
      "packagetype": "sdist",
      "python_version": "source",
      "requires_python": ">=3.10",
      "size": 108650,
      "upload_time": "2023-02-28T02:37:04",
      "upload_time_iso_8601": "2023-02-28T02:37:04.960343Z",
      "url": "https://files.pythonhosted.org/packages/18/ef/5dd8d1cc78fdc8c3d339b656a845fa7ac43c5327710775d08218a90e831a/leeger-2.1.0.tar.gz",
      "yanked": false,
      "yanked_reason": null
    }
  ],
  "vulnerabilities": []
}